{"v":"5.12.2","fr":25,"ip":0,"op":101,"w":600,"h":600,"nm":"Christmas Pudding ","ddd":0,"assets":[],"layers":[{"ddd":0,"ind":1,"ty":4,"nm":"flam 1","parent":13,"sr":1,"ks":{"o":{"a":0,"k":100,"ix":11},"r":{"a":0,"k":0,"ix":10},"p":{"a":0,"k":[301.829,184.877,0],"ix":2,"l":2},"a":{"a":0,"k":[3.742,33.68,0],"ix":1,"l":2},"s":{"a":1,"k":[{"i":{"x":[0.667,0.667,0.667],"y":[1,1,1]},"o":{"x":[0.333,0.333,0.333],"y":[0,0,0]},"t":23,"s":[0,0,100]},{"i":{"x":[0.667,0.667,0.667],"y":[1,1,1]},"o":{"x":[0.333,0.333,0.333],"y":[0,0,0]},"t":29,"s":[110,110,100]},{"i":{"x":[0.833,0.833,0.833],"y":[1,1,1]},"o":{"x":[0.333,0.333,0.333],"y":[0,0,0]},"t":35,"s":[100,100,100]},{"i":{"x":[0.833,0.833,0.833],"y":[1,1,1]},"o":{"x":[0.167,0.167,0.167],"y":[0,0,0]},"t":45,"s":[110,110,100]},{"i":{"x":[0.833,0.833,0.833],"y":[1,1,1]},"o":{"x":[0.167,0.167,0.167],"y":[0,0,0]},"t":55,"s":[100,100,100]},{"i":{"x":[0.833,0.833,0.833],"y":[1,1,1]},"o":{"x":[0.167,0.167,0.167],"y":[0,0,0]},"t":65,"s":[110,110,100]},{"t":75,"s":[100,100,100]}],"ix":6,"l":2}},"ao":0,"shapes":[{"ty":"gr","it":[{"ind":0,"ty":"sh","ix":1,"ks":{"a":0,"k":{"i":[[4.208,-5.242],[9.334,1.748],[2.382,2.408],[-0.822,8.151],[-0.835,2.12],[-2.466,3.551],[0.59,10.626],[-0.03,-0.114],[-7.66,-13.073],[-0.844,-5.302]],"o":[[0,0],[-3.329,-0.623],[-3.009,-3.041],[0.229,-2.267],[1.015,-2.578],[3.744,-5.392],[-0.007,-0.118],[0.837,3.206],[2.714,4.632],[0.939,5.9]],"v":[[12.619,26.497],[-1.818,32.29],[-10.585,27.58],[-16.44,10.916],[-14.773,4.318],[-9.452,-5.988],[-0.966,-32.448],[-0.776,-32.481],[10.625,-6.652],[16.099,8.359]],"c":true},"ix":2},"nm":"Path 1","mn":"ADBE Vector Shape - Group","hd":false},{"ty":"st","c":{"a":0,"k":[0,0,0,1],"ix":3},"o":{"a":0,"k":100,"ix":4},"w":{"a":0,"k":5,"ix":5},"lc":2,"lj":2,"bm":0,"nm":"Stroke 1","mn":"ADBE Vector Graphic - Stroke","hd":false},{"ty":"tr","p":{"a":0,"k":[0,0],"ix":2},"a":{"a":0,"k":[0,0],"ix":1},"s":{"a":0,"k":[100,100],"ix":3},"r":{"a":0,"k":0,"ix":6},"o":{"a":0,"k":100,"ix":7},"sk":{"a":0,"k":0,"ix":4},"sa":{"a":0,"k":0,"ix":5},"nm":"Transform"}],"nm":"Group 1","np":2,"cix":2,"bm":0,"ix":1,"mn":"ADBE Vector Group","hd":false}],"ip":0,"op":125,"st":0,"ct":1,"bm":0},{"ddd":0,"ind":2,"ty":4,"nm":"Layer 9","parent":1,"sr":1,"ks":{"o":{"a":0,"k":100,"ix":11},"r":{"a":0,"k":0,"ix":10},"p":{"a":0,"k":[0,0,0],"ix":2,"l":2},"a":{"a":0,"k":[0,0,0],"ix":1,"l":2},"s":{"a":0,"k":[100,100,100],"ix":6,"l":2}},"ao":0,"shapes":[{"ty":"gr","it":[{"ind":0,"ty":"sh","ix":1,"ks":{"a":0,"k":{"i":[[4.208,-5.242],[9.334,1.748],[2.382,2.408],[-0.822,8.151],[-0.835,2.12],[-2.466,3.551],[0.59,10.626],[-0.03,-0.114],[-7.66,-13.073],[-0.844,-5.302]],"o":[[0,0],[-3.329,-0.623],[-3.009,-3.041],[0.229,-2.267],[1.015,-2.578],[3.744,-5.392],[-0.007,-0.118],[0.837,3.206],[2.714,4.632],[0.939,5.9]],"v":[[12.619,26.497],[-1.818,32.29],[-10.585,27.58],[-16.44,10.916],[-14.773,4.318],[-9.452,-5.988],[-0.966,-32.448],[-0.776,-32.481],[10.625,-6.652],[16.099,8.359]],"c":true},"ix":2},"nm":"Path 1","mn":"ADBE Vector Shape - Group","hd":false},{"ty":"fl","c":{"a":0,"k":[0.980392158031,0.501960813999,0.113725490868,1],"ix":4},"o":{"a":0,"k":100,"ix":5},"r":1,"bm":0,"nm":"Fill 1","mn":"ADBE Vector Graphic - Fill","hd":false},{"ty":"tr","p":{"a":0,"k":[0,0],"ix":2},"a":{"a":0,"k":[0,0],"ix":1},"s":{"a":0,"k":[100,100],"ix":3},"r":{"a":0,"k":0,"ix":6},"o":{"a":0,"k":100,"ix":7},"sk":{"a":0,"k":0,"ix":4},"sa":{"a":0,"k":0,"ix":5},"nm":"Transform"}],"nm":"Group 1","np":2,"cix":2,"bm":0,"ix":1,"mn":"ADBE Vector Group","hd":false}],"ip":0,"op":125,"st":0,"ct":1,"bm":0},{"ddd":0,"ind":3,"ty":4,"nm":"flam 2","parent":13,"sr":1,"ks":{"o":{"a":0,"k":100,"ix":11},"r":{"a":0,"k":0,"ix":10},"p":{"a":0,"k":[300.582,187.194,0],"ix":2,"l":2},"a":{"a":0,"k":[2.495,53.638,0],"ix":1,"l":2},"s":{"a":1,"k":[{"i":{"x":[0.667,0.667,0.667],"y":[1,1,1]},"o":{"x":[0.333,0.333,0.333],"y":[0,0,0]},"t":23,"s":[0,0,100]},{"i":{"x":[0.667,0.667,0.667],"y":[1,1,1]},"o":{"x":[0.333,0.333,0.333],"y":[0,0,0]},"t":29,"s":[110,110,100]},{"i":{"x":[0.833,0.833,0.833],"y":[1,1,1]},"o":{"x":[0.333,0.333,0.333],"y":[0,0,0]},"t":35,"s":[100,100,100]},{"i":{"x":[0.833,0.833,0.833],"y":[1,1,1]},"o":{"x":[0.167,0.167,0.167],"y":[0,0,0]},"t":45,"s":[110,110,100]},{"i":{"x":[0.833,0.833,0.833],"y":[1,1,1]},"o":{"x":[0.167,0.167,0.167],"y":[0,0,0]},"t":55,"s":[100,100,100]},{"i":{"x":[0.833,0.833,0.833],"y":[1,1,1]},"o":{"x":[0.167,0.167,0.167],"y":[0,0,0]},"t":65,"s":[110,110,100]},{"t":75,"s":[100,100,100]}],"ix":6,"l":2}},"ao":0,"shapes":[{"ty":"gr","it":[{"ind":0,"ty":"sh","ix":1,"ks":{"a":0,"k":{"i":[[6.489,-8.082],[14.393,2.695],[3.673,3.712],[-1.267,12.568],[-1.287,3.269],[-3.802,5.475],[0.909,16.385],[-0.046,-0.176],[-11.811,-20.157],[-1.301,-8.175]],"o":[[0,0],[-5.133,-0.961],[-4.64,-4.69],[0.353,-3.496],[1.566,-3.975],[5.773,-8.313],[-0.01,-0.182],[1.29,4.943],[4.185,7.142],[1.448,9.098]],"v":[[19.458,40.856],[-2.803,49.789],[-16.321,42.525],[-25.349,16.832],[-22.778,6.659],[-14.573,-9.233],[-1.489,-50.032],[-1.196,-50.083],[16.382,-10.256],[24.823,12.89]],"c":true},"ix":2},"nm":"Path 1","mn":"ADBE Vector Shape - Group","hd":false},{"ty":"st","c":{"a":0,"k":[0,0,0,1],"ix":3},"o":{"a":0,"k":100,"ix":4},"w":{"a":0,"k":5,"ix":5},"lc":2,"lj":2,"bm":0,"nm":"Stroke 1","mn":"ADBE Vector Graphic - Stroke","hd":false},{"ty":"tr","p":{"a":0,"k":[0,0],"ix":2},"a":{"a":0,"k":[0,0],"ix":1},"s":{"a":0,"k":[100,100],"ix":3},"r":{"a":0,"k":0,"ix":6},"o":{"a":0,"k":100,"ix":7},"sk":{"a":0,"k":0,"ix":4},"sa":{"a":0,"k":0,"ix":5},"nm":"Transform"}],"nm":"Group 1","np":2,"cix":2,"bm":0,"ix":1,"mn":"ADBE Vector Group","hd":false}],"ip":0,"op":125,"st":0,"ct":1,"bm":0},{"ddd":0,"ind":4,"ty":4,"nm":"Layer 15","parent":3,"sr":1,"ks":{"o":{"a":0,"k":100,"ix":11},"r":{"a":0,"k":0,"ix":10},"p":{"a":0,"k":[0,0,0],"ix":2,"l":2},"a":{"a":0,"k":[0,0,0],"ix":1,"l":2},"s":{"a":0,"k":[100,100,100],"ix":6,"l":2}},"ao":0,"shapes":[{"ty":"gr","it":[{"ind":0,"ty":"sh","ix":1,"ks":{"a":0,"k":{"i":[[6.489,-8.082],[14.393,2.695],[3.673,3.712],[-1.267,12.568],[-1.287,3.269],[-3.802,5.475],[0.909,16.385],[-0.046,-0.176],[-11.811,-20.157],[-1.301,-8.175]],"o":[[0,0],[-5.133,-0.961],[-4.64,-4.69],[0.353,-3.496],[1.566,-3.975],[5.773,-8.313],[-0.01,-0.182],[1.29,4.943],[4.185,7.142],[1.448,9.098]],"v":[[19.458,40.856],[-2.803,49.789],[-16.321,42.525],[-25.349,16.832],[-22.778,6.659],[-14.573,-9.233],[-1.489,-50.032],[-1.196,-50.083],[16.382,-10.256],[24.823,12.89]],"c":true},"ix":2},"nm":"Path 1","mn":"ADBE Vector Shape - Group","hd":false},{"ty":"fl","c":{"a":0,"k":[1,0.713725507259,0,1],"ix":4},"o":{"a":0,"k":100,"ix":5},"r":1,"bm":0,"nm":"Fill 1","mn":"ADBE Vector Graphic - Fill","hd":false},{"ty":"tr","p":{"a":0,"k":[0,0],"ix":2},"a":{"a":0,"k":[0,0],"ix":1},"s":{"a":0,"k":[100,100],"ix":3},"r":{"a":0,"k":0,"ix":6},"o":{"a":0,"k":100,"ix":7},"sk":{"a":0,"k":0,"ix":4},"sa":{"a":0,"k":0,"ix":5},"nm":"Transform"}],"nm":"Group 1","np":2,"cix":2,"bm":0,"ix":1,"mn":"ADBE Vector Group","hd":false}],"ip":0,"op":125,"st":0,"ct":1,"bm":0},{"ddd":0,"ind":5,"ty":4,"nm":"Layer 13","parent":6,"sr":1,"ks":{"o":{"a":0,"k":100,"ix":11},"r":{"a":0,"k":0,"ix":10},"p":{"a":0,"k":[0,0,0],"ix":2,"l":2},"a":{"a":0,"k":[337.188,313.402,0],"ix":1,"l":2},"s":{"a":0,"k":[100,100,100],"ix":6,"l":2}},"ao":0,"shapes":[{"ty":"gr","it":[{"ty":"gr","it":[{"ind":0,"ty":"sh","ix":1,"ks":{"a":0,"k":{"i":[[-0.233,-1.04],[1.406,-0.315],[0.233,1.04],[-1.406,0.315]],"o":[[0.233,1.04],[-1.406,0.315],[-0.233,-1.04],[1.406,-0.315]],"v":[[2.546,-0.57],[0.421,1.883],[-2.546,0.57],[-0.421,-1.883]],"c":true},"ix":2},"nm":"Path 1","mn":"ADBE Vector Shape - Group","hd":false},{"ty":"fl","c":{"a":0,"k":[1,0.941176474094,0.945098042488,1],"ix":4},"o":{"a":0,"k":100,"ix":5},"r":1,"bm":0,"nm":"Fill 1","mn":"ADBE Vector Graphic - Fill","hd":false},{"ty":"tr","p":{"a":0,"k":[319.81,309.782],"ix":2},"a":{"a":0,"k":[0,0],"ix":1},"s":{"a":0,"k":[100,100],"ix":3},"r":{"a":0,"k":0,"ix":6},"o":{"a":0,"k":100,"ix":7},"sk":{"a":0,"k":0,"ix":4},"sa":{"a":0,"k":0,"ix":5},"nm":"Transform"}],"nm":"Group 1","np":2,"cix":2,"bm":0,"ix":1,"mn":"ADBE Vector Group","hd":false},{"ty":"gr","it":[{"ind":0,"ty":"sh","ix":1,"ks":{"a":0,"k":{"i":[[-0.289,-1.292],[1.747,-0.391],[0.289,1.292],[-1.747,0.391]],"o":[[0.289,1.292],[-1.747,0.391],[-0.289,-1.292],[1.747,-0.391]],"v":[[3.164,-0.708],[0.523,2.34],[-3.164,0.708],[-0.523,-2.34]],"c":true},"ix":2},"nm":"Path 1","mn":"ADBE Vector Shape - Group","hd":false},{"ty":"fl","c":{"a":0,"k":[1,0.941176474094,0.945098042488,1],"ix":4},"o":{"a":0,"k":100,"ix":5},"r":1,"bm":0,"nm":"Fill 1","mn":"ADBE Vector Graphic - Fill","hd":false},{"ty":"tr","p":{"a":0,"k":[330.438,312.318],"ix":2},"a":{"a":0,"k":[0,0],"ix":1},"s":{"a":0,"k":[100,100],"ix":3},"r":{"a":0,"k":0,"ix":6},"o":{"a":0,"k":100,"ix":7},"sk":{"a":0,"k":0,"ix":4},"sa":{"a":0,"k":0,"ix":5},"nm":"Transform"}],"nm":"Group 2","np":2,"cix":2,"bm":0,"ix":2,"mn":"ADBE Vector Group","hd":false},{"ty":"gr","it":[{"ind":0,"ty":"sh","ix":1,"ks":{"a":0,"k":{"i":[[-0.636,-2.844],[3.013,-0.674],[0.636,2.844],[-3.013,0.674]],"o":[[0.636,2.844],[-3.013,0.674],[-0.636,-2.844],[3.013,-0.674]],"v":[[5.455,-1.22],[1.152,5.15],[-5.455,1.22],[-1.152,-5.15]],"c":true},"ix":2},"nm":"Path 1","mn":"ADBE Vector Shape - Group","hd":false},{"ty":"fl","c":{"a":0,"k":[1,0.941176474094,0.945098042488,1],"ix":4},"o":{"a":0,"k":100,"ix":5},"r":1,"bm":0,"nm":"Fill 1","mn":"ADBE Vector Graphic - Fill","hd":false},{"ty":"tr","p":{"a":0,"k":[326.808,302.168],"ix":2},"a":{"a":0,"k":[0,0],"ix":1},"s":{"a":0,"k":[100,100],"ix":3},"r":{"a":0,"k":0,"ix":6},"o":{"a":0,"k":100,"ix":7},"sk":{"a":0,"k":0,"ix":4},"sa":{"a":0,"k":0,"ix":5},"nm":"Transform"}],"nm":"Group 3","np":2,"cix":2,"bm":0,"ix":3,"mn":"ADBE Vector Group","hd":false},{"ty":"tr","p":{"a":0,"k":[326.808,302.168],"ix":2},"a":{"a":0,"k":[326.808,302.168],"ix":1},"s":{"a":0,"k":[100,100],"ix":3},"r":{"a":0,"k":0,"ix":6},"o":{"a":0,"k":100,"ix":7},"sk":{"a":0,"k":0,"ix":4},"sa":{"a":0,"k":0,"ix":5},"nm":"Transform"}],"nm":"Group 1","np":3,"cix":2,"bm":0,"ix":1,"mn":"ADBE Vector Group","hd":false},{"ty":"gr","it":[{"ind":0,"ty":"sh","ix":1,"ks":{"a":0,"k":{"i":[[-2.281,-9.377],[9.609,-2.337],[2.281,9.377],[-9.609,2.337]],"o":[[2.281,9.377],[-9.609,2.337],[-2.281,-9.377],[9.609,-2.337]],"v":[[17.399,-4.232],[4.13,16.979],[-17.399,4.232],[-4.13,-16.979]],"c":true},"ix":2},"nm":"Path 1","mn":"ADBE Vector Shape - Group","hd":false},{"ty":"fl","c":{"a":0,"k":[0.831372559071,0.188235297799,0.188235297799,1],"ix":4},"o":{"a":0,"k":100,"ix":5},"r":1,"bm":0,"nm":"Fill 1","mn":"ADBE Vector Graphic - Fill","hd":false},{"ty":"tr","p":{"a":0,"k":[333.707,311.436],"ix":2},"a":{"a":0,"k":[0,0],"ix":1},"s":{"a":0,"k":[100,100],"ix":3},"r":{"a":0,"k":0,"ix":6},"o":{"a":0,"k":100,"ix":7},"sk":{"a":0,"k":0,"ix":4},"sa":{"a":0,"k":0,"ix":5},"nm":"Transform"}],"nm":"Group 2","np":2,"cix":2,"bm":0,"ix":2,"mn":"ADBE Vector Group","hd":false},{"ty":"gr","it":[{"ind":0,"ty":"sh","ix":1,"ks":{"a":0,"k":{"i":[[-3.125,-12.848],[13.165,-3.202],[3.125,12.848],[-13.165,3.202]],"o":[[3.125,12.848],[-13.165,3.202],[-3.125,-12.848],[13.165,-3.202]],"v":[[23.838,-5.798],[5.659,23.263],[-23.838,5.798],[-5.659,-23.263]],"c":true},"ix":2},"nm":"Path 1","mn":"ADBE Vector Shape - Group","hd":false},{"ty":"fl","c":{"a":0,"k":[0.600000023842,0.105882354081,0.113725490868,1],"ix":4},"o":{"a":0,"k":100,"ix":5},"r":1,"bm":0,"nm":"Fill 1","mn":"ADBE Vector Graphic - Fill","hd":false},{"ty":"tr","p":{"a":0,"k":[337.188,313.402],"ix":2},"a":{"a":0,"k":[0,0],"ix":1},"s":{"a":0,"k":[100,100],"ix":3},"r":{"a":0,"k":0,"ix":6},"o":{"a":0,"k":100,"ix":7},"sk":{"a":0,"k":0,"ix":4},"sa":{"a":0,"k":0,"ix":5},"nm":"Transform"}],"nm":"Group 3","np":2,"cix":2,"bm":0,"ix":3,"mn":"ADBE Vector Group","hd":false}],"ip":0,"op":125,"st":0,"ct":1,"bm":0},{"ddd":0,"ind":6,"ty":4,"nm":"f 3","parent":13,"sr":1,"ks":{"o":{"a":0,"k":100,"ix":11},"r":{"a":1,"k":[{"i":{"x":[0.667],"y":[1]},"o":{"x":[0.333],"y":[0]},"t":45,"s":[0]},{"i":{"x":[0.667],"y":[1]},"o":{"x":[0.333],"y":[0]},"t":55,"s":[10]},{"i":{"x":[0.667],"y":[1]},"o":{"x":[0.333],"y":[0]},"t":65,"s":[-10]},{"t":75,"s":[5]}],"ix":10},"p":{"a":0,"k":[337.188,313.402,0],"ix":2,"l":2},"a":{"a":0,"k":[0,0,0],"ix":1,"l":2},"s":{"a":1,"k":[{"i":{"x":[0.667,0.667,0.667],"y":[0.773,0.773,-24]},"o":{"x":[0.333,0.333,0.333],"y":[0,0,0]},"t":23,"s":[0,0,100]},{"i":{"x":[0.667,0.667,0.667],"y":[1,1,1]},"o":{"x":[0.333,0.333,0.333],"y":[-2.5,-2.5,25]},"t":29,"s":[110,110,100]},{"t":35,"s":[100,100,100]}],"ix":6,"l":2}},"ao":0,"shapes":[{"ty":"gr","it":[{"ind":0,"ty":"sh","ix":1,"ks":{"a":0,"k":{"i":[[-3.125,-12.848],[13.165,-3.202],[3.125,12.848],[-13.165,3.202]],"o":[[3.125,12.848],[-13.165,3.202],[-3.125,-12.848],[13.165,-3.202]],"v":[[23.838,-5.798],[5.659,23.263],[-23.838,5.798],[-5.659,-23.263]],"c":true},"ix":2},"nm":"Path 1","mn":"ADBE Vector Shape - Group","hd":false},{"ty":"st","c":{"a":0,"k":[0,0,0,1],"ix":3},"o":{"a":0,"k":100,"ix":4},"w":{"a":0,"k":7,"ix":5},"lc":2,"lj":2,"bm":0,"nm":"Stroke 1","mn":"ADBE Vector Graphic - Stroke","hd":false},{"ty":"tr","p":{"a":0,"k":[0,0],"ix":2},"a":{"a":0,"k":[0,0],"ix":1},"s":{"a":0,"k":[100,100],"ix":3},"r":{"a":0,"k":0,"ix":6},"o":{"a":0,"k":100,"ix":7},"sk":{"a":0,"k":0,"ix":4},"sa":{"a":0,"k":0,"ix":5},"nm":"Transform"}],"nm":"Group 1","np":2,"cix":2,"bm":0,"ix":1,"mn":"ADBE Vector Group","hd":false}],"ip":0,"op":125,"st":0,"ct":1,"bm":0},{"ddd":0,"ind":7,"ty":4,"nm":"Layer 11","parent":8,"sr":1,"ks":{"o":{"a":0,"k":100,"ix":11},"r":{"a":0,"k":0,"ix":10},"p":{"a":0,"k":[0,0,0],"ix":2,"l":2},"a":{"a":0,"k":[268.418,313.402,0],"ix":1,"l":2},"s":{"a":0,"k":[100,100,100],"ix":6,"l":2}},"ao":0,"shapes":[{"ty":"gr","it":[{"ty":"gr","it":[{"ind":0,"ty":"sh","ix":1,"ks":{"a":0,"k":{"i":[[-0.233,-1.04],[1.406,-0.315],[0.233,1.04],[-1.406,0.315]],"o":[[0.233,1.04],[-1.406,0.315],[-0.233,-1.04],[1.406,-0.315]],"v":[[2.546,-0.57],[0.421,1.883],[-2.546,0.57],[-0.421,-1.883]],"c":true},"ix":2},"nm":"Path 1","mn":"ADBE Vector Shape - Group","hd":false},{"ty":"fl","c":{"a":0,"k":[1,0.941176474094,0.945098042488,1],"ix":4},"o":{"a":0,"k":100,"ix":5},"r":1,"bm":0,"nm":"Fill 1","mn":"ADBE Vector Graphic - Fill","hd":false},{"ty":"tr","p":{"a":0,"k":[251.04,309.782],"ix":2},"a":{"a":0,"k":[0,0],"ix":1},"s":{"a":0,"k":[100,100],"ix":3},"r":{"a":0,"k":0,"ix":6},"o":{"a":0,"k":100,"ix":7},"sk":{"a":0,"k":0,"ix":4},"sa":{"a":0,"k":0,"ix":5},"nm":"Transform"}],"nm":"Group 1","np":2,"cix":2,"bm":0,"ix":1,"mn":"ADBE Vector Group","hd":false},{"ty":"gr","it":[{"ind":0,"ty":"sh","ix":1,"ks":{"a":0,"k":{"i":[[-0.289,-1.292],[1.747,-0.391],[0.289,1.292],[-1.747,0.391]],"o":[[0.289,1.292],[-1.747,0.391],[-0.289,-1.292],[1.747,-0.391]],"v":[[3.164,-0.708],[0.523,2.34],[-3.164,0.708],[-0.523,-2.34]],"c":true},"ix":2},"nm":"Path 1","mn":"ADBE Vector Shape - Group","hd":false},{"ty":"fl","c":{"a":0,"k":[1,0.941176474094,0.945098042488,1],"ix":4},"o":{"a":0,"k":100,"ix":5},"r":1,"bm":0,"nm":"Fill 1","mn":"ADBE Vector Graphic - Fill","hd":false},{"ty":"tr","p":{"a":0,"k":[261.668,312.318],"ix":2},"a":{"a":0,"k":[0,0],"ix":1},"s":{"a":0,"k":[100,100],"ix":3},"r":{"a":0,"k":0,"ix":6},"o":{"a":0,"k":100,"ix":7},"sk":{"a":0,"k":0,"ix":4},"sa":{"a":0,"k":0,"ix":5},"nm":"Transform"}],"nm":"Group 2","np":2,"cix":2,"bm":0,"ix":2,"mn":"ADBE Vector Group","hd":false},{"ty":"gr","it":[{"ind":0,"ty":"sh","ix":1,"ks":{"a":0,"k":{"i":[[-0.636,-2.844],[3.013,-0.674],[0.636,2.844],[-3.013,0.674]],"o":[[0.636,2.844],[-3.013,0.674],[-0.636,-2.844],[3.013,-0.674]],"v":[[5.455,-1.22],[1.152,5.15],[-5.455,1.22],[-1.152,-5.15]],"c":true},"ix":2},"nm":"Path 1","mn":"ADBE Vector Shape - Group","hd":false},{"ty":"fl","c":{"a":0,"k":[1,0.941176474094,0.945098042488,1],"ix":4},"o":{"a":0,"k":100,"ix":5},"r":1,"bm":0,"nm":"Fill 1","mn":"ADBE Vector Graphic - Fill","hd":false},{"ty":"tr","p":{"a":0,"k":[258.038,302.168],"ix":2},"a":{"a":0,"k":[0,0],"ix":1},"s":{"a":0,"k":[100,100],"ix":3},"r":{"a":0,"k":0,"ix":6},"o":{"a":0,"k":100,"ix":7},"sk":{"a":0,"k":0,"ix":4},"sa":{"a":0,"k":0,"ix":5},"nm":"Transform"}],"nm":"Group 3","np":2,"cix":2,"bm":0,"ix":3,"mn":"ADBE Vector Group","hd":false},{"ty":"tr","p":{"a":0,"k":[258.038,302.168],"ix":2},"a":{"a":0,"k":[258.038,302.168],"ix":1},"s":{"a":0,"k":[100,100],"ix":3},"r":{"a":0,"k":0,"ix":6},"o":{"a":0,"k":100,"ix":7},"sk":{"a":0,"k":0,"ix":4},"sa":{"a":0,"k":0,"ix":5},"nm":"Transform"}],"nm":"Group 1","np":3,"cix":2,"bm":0,"ix":1,"mn":"ADBE Vector Group","hd":false},{"ty":"gr","it":[{"ind":0,"ty":"sh","ix":1,"ks":{"a":0,"k":{"i":[[-2.281,-9.377],[9.609,-2.337],[2.281,9.377],[-9.609,2.337]],"o":[[2.281,9.377],[-9.609,2.337],[-2.281,-9.377],[9.609,-2.337]],"v":[[17.399,-4.232],[4.13,16.979],[-17.399,4.232],[-4.13,-16.979]],"c":true},"ix":2},"nm":"Path 1","mn":"ADBE Vector Shape - Group","hd":false},{"ty":"fl","c":{"a":0,"k":[0.831372559071,0.188235297799,0.188235297799,1],"ix":4},"o":{"a":0,"k":100,"ix":5},"r":1,"bm":0,"nm":"Fill 1","mn":"ADBE Vector Graphic - Fill","hd":false},{"ty":"tr","p":{"a":0,"k":[264.937,311.436],"ix":2},"a":{"a":0,"k":[0,0],"ix":1},"s":{"a":0,"k":[100,100],"ix":3},"r":{"a":0,"k":0,"ix":6},"o":{"a":0,"k":100,"ix":7},"sk":{"a":0,"k":0,"ix":4},"sa":{"a":0,"k":0,"ix":5},"nm":"Transform"}],"nm":"Group 2","np":2,"cix":2,"bm":0,"ix":2,"mn":"ADBE Vector Group","hd":false},{"ty":"gr","it":[{"ind":0,"ty":"sh","ix":1,"ks":{"a":0,"k":{"i":[[-3.125,-12.848],[13.165,-3.202],[3.125,12.848],[-13.165,3.202]],"o":[[3.125,12.848],[-13.165,3.202],[-3.125,-12.848],[13.165,-3.202]],"v":[[23.838,-5.798],[5.659,23.263],[-23.838,5.798],[-5.659,-23.263]],"c":true},"ix":2},"nm":"Path 1","mn":"ADBE Vector Shape - Group","hd":false},{"ty":"fl","c":{"a":0,"k":[0.600000023842,0.105882354081,0.113725490868,1],"ix":4},"o":{"a":0,"k":100,"ix":5},"r":1,"bm":0,"nm":"Fill 1","mn":"ADBE Vector Graphic - Fill","hd":false},{"ty":"tr","p":{"a":0,"k":[268.418,313.402],"ix":2},"a":{"a":0,"k":[0,0],"ix":1},"s":{"a":0,"k":[100,100],"ix":3},"r":{"a":0,"k":0,"ix":6},"o":{"a":0,"k":100,"ix":7},"sk":{"a":0,"k":0,"ix":4},"sa":{"a":0,"k":0,"ix":5},"nm":"Transform"}],"nm":"Group 3","np":2,"cix":2,"bm":0,"ix":3,"mn":"ADBE Vector Group","hd":false}],"ip":0,"op":125,"st":0,"ct":1,"bm":0},{"ddd":0,"ind":8,"ty":4,"nm":"f 1","parent":13,"sr":1,"ks":{"o":{"a":0,"k":100,"ix":11},"r":{"a":1,"k":[{"i":{"x":[0.667],"y":[1]},"o":{"x":[0.333],"y":[0]},"t":45,"s":[0]},{"i":{"x":[0.667],"y":[1]},"o":{"x":[0.333],"y":[0]},"t":55,"s":[10]},{"i":{"x":[0.667],"y":[1]},"o":{"x":[0.333],"y":[0]},"t":65,"s":[-10]},{"t":75,"s":[5]}],"ix":10},"p":{"a":0,"k":[268.418,313.402,0],"ix":2,"l":2},"a":{"a":0,"k":[0,0,0],"ix":1,"l":2},"s":{"a":1,"k":[{"i":{"x":[0.667,0.667,0.667],"y":[0.773,0.773,-24]},"o":{"x":[0.333,0.333,0.333],"y":[0,0,0]},"t":23,"s":[0,0,100]},{"i":{"x":[0.667,0.667,0.667],"y":[1,1,1]},"o":{"x":[0.333,0.333,0.333],"y":[-2.5,-2.5,25]},"t":29,"s":[110,110,100]},{"t":35,"s":[100,100,100]}],"ix":6,"l":2}},"ao":0,"shapes":[{"ty":"gr","it":[{"ind":0,"ty":"sh","ix":1,"ks":{"a":0,"k":{"i":[[-3.125,-12.848],[13.165,-3.202],[3.125,12.848],[-13.165,3.202]],"o":[[3.125,12.848],[-13.165,3.202],[-3.125,-12.848],[13.165,-3.202]],"v":[[23.838,-5.798],[5.659,23.263],[-23.838,5.798],[-5.659,-23.263]],"c":true},"ix":2},"nm":"Path 1","mn":"ADBE Vector Shape - Group","hd":false},{"ty":"st","c":{"a":0,"k":[0,0,0,1],"ix":3},"o":{"a":0,"k":100,"ix":4},"w":{"a":0,"k":7,"ix":5},"lc":2,"lj":2,"bm":0,"nm":"Stroke 1","mn":"ADBE Vector Graphic - Stroke","hd":false},{"ty":"tr","p":{"a":0,"k":[0,0],"ix":2},"a":{"a":0,"k":[0,0],"ix":1},"s":{"a":0,"k":[100,100],"ix":3},"r":{"a":0,"k":0,"ix":6},"o":{"a":0,"k":100,"ix":7},"sk":{"a":0,"k":0,"ix":4},"sa":{"a":0,"k":0,"ix":5},"nm":"Transform"}],"nm":"Group 1","np":2,"cix":2,"bm":0,"ix":1,"mn":"ADBE Vector Group","hd":false}],"ip":0,"op":125,"st":0,"ct":1,"bm":0},{"ddd":0,"ind":9,"ty":4,"nm":"Layer 12","parent":10,"sr":1,"ks":{"o":{"a":0,"k":100,"ix":11},"r":{"a":0,"k":0,"ix":10},"p":{"a":0,"k":[0,0,0],"ix":2,"l":2},"a":{"a":0,"k":[300,292.274,0],"ix":1,"l":2},"s":{"a":0,"k":[100,100,100],"ix":6,"l":2}},"ao":0,"shapes":[{"ty":"gr","it":[{"ty":"gr","it":[{"ind":0,"ty":"sh","ix":1,"ks":{"a":0,"k":{"i":[[0.05,-1.064],[1.439,0.067],[-0.05,1.064],[-1.439,-0.067]],"o":[[-0.05,1.064],[-1.439,-0.067],[0.05,-1.064],[1.439,0.067]],"v":[[2.606,0.122],[-0.09,1.927],[-2.606,-0.122],[0.09,-1.927]],"c":true},"ix":2},"nm":"Path 1","mn":"ADBE Vector Shape - Group","hd":false},{"ty":"fl","c":{"a":0,"k":[1,0.941176474094,0.945098042488,1],"ix":4},"o":{"a":0,"k":100,"ix":5},"r":1,"bm":0,"nm":"Fill 1","mn":"ADBE Vector Graphic - Fill","hd":false},{"ty":"tr","p":{"a":0,"k":[284.193,284.199],"ix":2},"a":{"a":0,"k":[0,0],"ix":1},"s":{"a":0,"k":[100,100],"ix":3},"r":{"a":0,"k":0,"ix":6},"o":{"a":0,"k":100,"ix":7},"sk":{"a":0,"k":0,"ix":4},"sa":{"a":0,"k":0,"ix":5},"nm":"Transform"}],"nm":"Group 1","np":2,"cix":2,"bm":0,"ix":1,"mn":"ADBE Vector Group","hd":false},{"ty":"gr","it":[{"ind":0,"ty":"sh","ix":1,"ks":{"a":0,"k":{"i":[[0.062,-1.323],[1.788,0.084],[-0.062,1.323],[-1.788,-0.084]],"o":[[-0.062,1.323],[-1.788,-0.084],[0.062,-1.323],[1.788,0.084]],"v":[[3.238,0.152],[-0.112,2.395],[-3.238,-0.152],[0.112,-2.395]],"c":true},"ix":2},"nm":"Path 1","mn":"ADBE Vector Shape - Group","hd":false},{"ty":"fl","c":{"a":0,"k":[1,0.941176474094,0.945098042488,1],"ix":4},"o":{"a":0,"k":100,"ix":5},"r":1,"bm":0,"nm":"Fill 1","mn":"ADBE Vector Graphic - Fill","hd":false},{"ty":"tr","p":{"a":0,"k":[293.775,289.448],"ix":2},"a":{"a":0,"k":[0,0],"ix":1},"s":{"a":0,"k":[100,100],"ix":3},"r":{"a":0,"k":0,"ix":6},"o":{"a":0,"k":100,"ix":7},"sk":{"a":0,"k":0,"ix":4},"sa":{"a":0,"k":0,"ix":5},"nm":"Transform"}],"nm":"Group 2","np":2,"cix":2,"bm":0,"ix":2,"mn":"ADBE Vector Group","hd":false},{"ty":"gr","it":[{"ind":0,"ty":"sh","ix":1,"ks":{"a":0,"k":{"i":[[0.136,-2.912],[3.084,0.145],[-0.136,2.912],[-3.084,-0.145]],"o":[[-0.136,2.912],[-3.084,-0.145],[0.136,-2.912],[3.084,0.145]],"v":[[5.584,0.262],[-0.247,5.272],[-5.584,-0.262],[0.247,-5.272]],"c":true},"ix":2},"nm":"Path 1","mn":"ADBE Vector Shape - Group","hd":false},{"ty":"fl","c":{"a":0,"k":[1,0.941176474094,0.945098042488,1],"ix":4},"o":{"a":0,"k":100,"ix":5},"r":1,"bm":0,"nm":"Fill 1","mn":"ADBE Vector Graphic - Fill","hd":false},{"ty":"tr","p":{"a":0,"k":[292.95,278.701],"ix":2},"a":{"a":0,"k":[0,0],"ix":1},"s":{"a":0,"k":[100,100],"ix":3},"r":{"a":0,"k":0,"ix":6},"o":{"a":0,"k":100,"ix":7},"sk":{"a":0,"k":0,"ix":4},"sa":{"a":0,"k":0,"ix":5},"nm":"Transform"}],"nm":"Group 3","np":2,"cix":2,"bm":0,"ix":3,"mn":"ADBE Vector Group","hd":false},{"ty":"tr","p":{"a":0,"k":[292.95,278.701],"ix":2},"a":{"a":0,"k":[292.95,278.701],"ix":1},"s":{"a":0,"k":[100,100],"ix":3},"r":{"a":0,"k":0,"ix":6},"o":{"a":0,"k":100,"ix":7},"sk":{"a":0,"k":0,"ix":4},"sa":{"a":0,"k":0,"ix":5},"nm":"Transform"}],"nm":"Group 1","np":3,"cix":2,"bm":0,"ix":1,"mn":"ADBE Vector Group","hd":false},{"ty":"gr","it":[{"ind":0,"ty":"sh","ix":1,"ks":{"a":0,"k":{"i":[[0.273,-9.647],[9.885,0.28],[-0.273,9.647],[-9.885,-0.28]],"o":[[-0.273,9.647],[-9.885,-0.28],[0.273,-9.647],[9.885,0.28]],"v":[[17.899,0.507],[-0.494,17.467],[-17.899,-0.507],[0.494,-17.467]],"c":true},"ix":2},"nm":"Path 1","mn":"ADBE Vector Shape - Group","hd":false},{"ty":"fl","c":{"a":0,"k":[0.831372559071,0.188235297799,0.188235297799,1],"ix":4},"o":{"a":0,"k":100,"ix":5},"r":1,"bm":0,"nm":"Fill 1","mn":"ADBE Vector Graphic - Fill","hd":false},{"ty":"tr","p":{"a":0,"k":[297.161,289.46],"ix":2},"a":{"a":0,"k":[0,0],"ix":1},"s":{"a":0,"k":[100,100],"ix":3},"r":{"a":0,"k":0,"ix":6},"o":{"a":0,"k":100,"ix":7},"sk":{"a":0,"k":0,"ix":4},"sa":{"a":0,"k":0,"ix":5},"nm":"Transform"}],"nm":"Group 2","np":2,"cix":2,"bm":0,"ix":2,"mn":"ADBE Vector Group","hd":false},{"ty":"gr","it":[{"ind":0,"ty":"sh","ix":1,"ks":{"a":0,"k":{"i":[[0.374,-13.217],[13.544,0.383],[-0.374,13.217],[-13.544,-0.383]],"o":[[-0.374,13.217],[-13.544,-0.383],[0.374,-13.217],[13.544,0.383]],"v":[[24.523,0.694],[-0.677,23.932],[-24.523,-0.694],[0.677,-23.932]],"c":true},"ix":2},"nm":"Path 1","mn":"ADBE Vector Shape - Group","hd":false},{"ty":"fl","c":{"a":0,"k":[0.600000023842,0.105882354081,0.113725490868,1],"ix":4},"o":{"a":0,"k":100,"ix":5},"r":1,"bm":0,"nm":"Fill 1","mn":"ADBE Vector Graphic - Fill","hd":false},{"ty":"tr","p":{"a":0,"k":[300,292.274],"ix":2},"a":{"a":0,"k":[0,0],"ix":1},"s":{"a":0,"k":[100,100],"ix":3},"r":{"a":0,"k":0,"ix":6},"o":{"a":0,"k":100,"ix":7},"sk":{"a":0,"k":0,"ix":4},"sa":{"a":0,"k":0,"ix":5},"nm":"Transform"}],"nm":"Group 3","np":2,"cix":2,"bm":0,"ix":3,"mn":"ADBE Vector Group","hd":false}],"ip":0,"op":125,"st":0,"ct":1,"bm":0},{"ddd":0,"ind":10,"ty":4,"nm":"f 2","parent":13,"sr":1,"ks":{"o":{"a":0,"k":100,"ix":11},"r":{"a":1,"k":[{"i":{"x":[0.667],"y":[1]},"o":{"x":[0.333],"y":[0]},"t":45,"s":[0]},{"i":{"x":[0.667],"y":[1]},"o":{"x":[0.333],"y":[0]},"t":55,"s":[-10]},{"i":{"x":[0.667],"y":[1]},"o":{"x":[0.333],"y":[0]},"t":65,"s":[10]},{"t":75,"s":[-5]}],"ix":10},"p":{"a":0,"k":[300,292.274,0],"ix":2,"l":2},"a":{"a":0,"k":[0,0,0],"ix":1,"l":2},"s":{"a":1,"k":[{"i":{"x":[0.667,0.667,0.667],"y":[0.773,0.773,-24]},"o":{"x":[0.333,0.333,0.333],"y":[0,0,0]},"t":23,"s":[0,0,100]},{"i":{"x":[0.667,0.667,0.667],"y":[1,1,1]},"o":{"x":[0.333,0.333,0.333],"y":[-2.5,-2.5,25]},"t":29,"s":[110,110,100]},{"t":35,"s":[100,100,100]}],"ix":6,"l":2}},"ao":0,"shapes":[{"ty":"gr","it":[{"ind":0,"ty":"sh","ix":1,"ks":{"a":0,"k":{"i":[[0.374,-13.217],[13.544,0.383],[-0.374,13.217],[-13.544,-0.383]],"o":[[-0.374,13.217],[-13.544,-0.383],[0.374,-13.217],[13.544,0.383]],"v":[[24.523,0.694],[-0.677,23.932],[-24.523,-0.694],[0.677,-23.932]],"c":true},"ix":2},"nm":"Path 1","mn":"ADBE Vector Shape - Group","hd":false},{"ty":"st","c":{"a":0,"k":[0,0,0,1],"ix":3},"o":{"a":0,"k":100,"ix":4},"w":{"a":0,"k":7,"ix":5},"lc":2,"lj":2,"bm":0,"nm":"Stroke 1","mn":"ADBE Vector Graphic - Stroke","hd":false},{"ty":"tr","p":{"a":0,"k":[0,0],"ix":2},"a":{"a":0,"k":[0,0],"ix":1},"s":{"a":0,"k":[100,100],"ix":3},"r":{"a":0,"k":0,"ix":6},"o":{"a":0,"k":100,"ix":7},"sk":{"a":0,"k":0,"ix":4},"sa":{"a":0,"k":0,"ix":5},"nm":"Transform"}],"nm":"Group 1","np":2,"cix":2,"bm":0,"ix":1,"mn":"ADBE Vector Group","hd":false}],"ip":0,"op":125,"st":0,"ct":1,"bm":0},{"ddd":0,"ind":11,"ty":4,"nm":"Layer 16","parent":12,"sr":1,"ks":{"o":{"a":0,"k":100,"ix":11},"r":{"a":0,"k":0,"ix":10},"p":{"a":0,"k":[0,0,0],"ix":2,"l":2},"a":{"a":0,"k":[0,0,0],"ix":1,"l":2},"s":{"a":0,"k":[100,100,100],"ix":6,"l":2}},"ao":0,"shapes":[{"ty":"gr","it":[{"ind":0,"ty":"sh","ix":1,"ks":{"a":0,"k":{"i":[[-0.441,-23.768],[56.05,-1.039],[0.441,23.768],[-56.05,1.039]],"o":[[0.441,23.768],[-56.05,1.039],[-0.441,-23.768],[56.05,-1.039]],"v":[[101.488,-1.881],[0.798,43.036],[-101.488,1.881],[-0.798,-43.036]],"c":true},"ix":2},"nm":"Path 1","mn":"ADBE Vector Shape - Group","hd":false},{"ty":"tr","p":{"a":0,"k":[0,0],"ix":2},"a":{"a":0,"k":[0,0],"ix":1},"s":{"a":0,"k":[100,100],"ix":3},"r":{"a":0,"k":0,"ix":6},"o":{"a":0,"k":100,"ix":7},"sk":{"a":0,"k":0,"ix":4},"sa":{"a":0,"k":0,"ix":5},"nm":"Transform"}],"nm":"Group 1","np":1,"cix":2,"bm":0,"ix":1,"mn":"ADBE Vector Group","hd":false}],"ip":0,"op":125,"st":0,"ct":1,"bm":0},{"ddd":0,"ind":12,"ty":4,"nm":"Layer 14","parent":13,"sr":1,"ks":{"o":{"a":0,"k":100,"ix":11},"r":{"a":0,"k":0,"ix":10},"p":{"a":0,"k":[299.917,339.08,0],"ix":2,"l":2},"a":{"a":0,"k":[0,0,0],"ix":1,"l":2},"s":{"a":0,"k":[100,100,100],"ix":6,"l":2}},"ao":0,"shapes":[{"ty":"gr","it":[{"ind":0,"ty":"sh","ix":1,"ks":{"a":0,"k":{"i":[[-0.441,-23.768],[56.05,-1.039],[0.441,23.768],[-56.05,1.039]],"o":[[0.441,23.768],[-56.05,1.039],[-0.441,-23.768],[56.05,-1.039]],"v":[[101.488,-1.881],[0.798,43.036],[-101.488,1.881],[-0.798,-43.036]],"c":true},"ix":2},"nm":"Path 1","mn":"ADBE Vector Shape - Group","hd":false},{"ty":"st","c":{"a":0,"k":[0,0,0,1],"ix":3},"o":{"a":0,"k":100,"ix":4},"w":{"a":0,"k":7,"ix":5},"lc":2,"lj":2,"bm":0,"nm":"Stroke 1","mn":"ADBE Vector Graphic - Stroke","hd":false},{"ty":"tr","p":{"a":0,"k":[0,0],"ix":2},"a":{"a":0,"k":[0,0],"ix":1},"s":{"a":0,"k":[100,100],"ix":3},"r":{"a":0,"k":0,"ix":6},"o":{"a":0,"k":100,"ix":7},"sk":{"a":0,"k":0,"ix":4},"sa":{"a":0,"k":0,"ix":5},"nm":"Transform"}],"nm":"Group 1","np":2,"cix":2,"bm":0,"ix":1,"mn":"ADBE Vector Group","hd":false}],"ip":0,"op":125,"st":0,"ct":1,"bm":0},{"ddd":0,"ind":13,"ty":4,"nm":"main layer","sr":1,"ks":{"o":{"a":0,"k":100,"ix":11},"r":{"a":0,"k":0,"ix":10},"p":{"a":0,"k":[305.445,535.741,0],"ix":2,"l":2},"a":{"a":0,"k":[305.445,535.741,0],"ix":1,"l":2},"s":{"a":1,"k":[{"i":{"x":[0.667,0.667,0.667],"y":[1,1,1]},"o":{"x":[0.333,0.333,0.333],"y":[0,0,0]},"t":10,"s":[50,0,100]},{"i":{"x":[0.667,0.667,0.667],"y":[1,1,1]},"o":{"x":[0.333,0.333,0.333],"y":[0,0,0]},"t":23,"s":[100,110,100]},{"t":35,"s":[100,100,100]}],"ix":6,"l":2}},"ao":0,"shapes":[{"ty":"gr","it":[{"ind":0,"ty":"sh","ix":1,"ks":{"a":0,"k":{"i":[[0,0],[10.832,-5.394],[37.243,14.263],[1.858,12.175],[-0.147,2.391],[0,0],[-12.706,11.605],[-0.473,0.417],[2.106,-40.064],[-7.937,14.554],[-5.682,4.543],[-0.513,-15.952],[-2.167,-9.643],[-13.815,20.212],[-6.604,14.312],[-7.827,-15.599],[1.003,-41.928],[11.318,-11.073],[-27.239,-11.557],[-4.025,22.254],[7.265,9.183],[-4.919,21.827],[-8.652,11.589],[-6.506,-16.509],[-5.797,-6.327],[-8.731,19.006],[-3.582,22.237],[-12.276,-16.724],[-4.091,-5.69],[-2.911,10.701],[0.05,14.857],[-20.794,-21.342],[-0.815,-7.922],[7.031,-15.649],[-14.722,-4.825],[2.616,21.679],[5.162,3.456],[1.349,13.279],[0,0],[-3.87,-5.469],[-1.587,-1.751],[0.299,4.423],[-0.008,8.945]],"o":[[0.224,12.101],[-104.684,52.126],[-11.507,-4.407],[-0.326,-2.104],[0,0],[2.623,-17.008],[0.455,-0.416],[-9.251,10.175],[0,0],[0,0],[0,0],[0,0],[0,0],[0,0],[0,0],[0,0],[0,0],[0,0],[0,0],[0,0],[0,0],[0,0],[0,0],[0,0],[0,0],[0,0],[0,0],[0,0],[0,0],[0,0],[0,0],[0,0],[0,0],[0,0],[0,0],[0,0],[0,0],[0,0],[0,0],[0,0],[1.578,1.742],[0,0],[0,0]],"v":[[163.985,42.963],[145.962,70.869],[-140.148,82.684],[-163.636,58.431],[-163.926,51.698],[-147.264,-56.351],[-123.747,-100.696],[-122.355,-101.946],[-145.288,-31.128],[-137.052,-29.501],[-119.867,-59.536],[-108.24,-53.985],[-110.574,-0.431],[-93.902,1.848],[-76.078,-29.302],[-57.482,-30.976],[-51.678,30.999],[-61.512,50.468],[-51.34,84.868],[-28.395,66.701],[-33.623,47.954],[-35.28,18.494],[-22.247,-19.983],[-5.785,-16.858],[9.903,23.205],[28.564,17.979],[36.762,-18.533],[54.884,-21.413],[70.015,5.461],[79.28,2.624],[83.276,-32.924],[105.799,-37.771],[117.28,-16.647],[114.041,0.208],[124.582,18.414],[140.865,-0.289],[134.055,-8.812],[127.102,-25.087],[122.484,-58.704],[126.453,-60.107],[133.751,-49.152],[138.35,-52.121],[138.731,-67.638]],"c":true},"ix":2},"nm":"Path 1","mn":"ADBE Vector Shape - Group","hd":false},{"ty":"st","c":{"a":0,"k":[0,0,0,1],"ix":3},"o":{"a":0,"k":100,"ix":4},"w":{"a":0,"k":7,"ix":5},"lc":2,"lj":2,"bm":0,"nm":"Stroke 1","mn":"ADBE Vector Graphic - Stroke","hd":false},{"ty":"tr","p":{"a":0,"k":[302.95,429.712],"ix":2},"a":{"a":0,"k":[0,0],"ix":1},"s":{"a":0,"k":[100,100],"ix":3},"r":{"a":0,"k":0,"ix":6},"o":{"a":0,"k":100,"ix":7},"sk":{"a":0,"k":0,"ix":4},"sa":{"a":0,"k":0,"ix":5},"nm":"Transform"}],"nm":"Group 1","np":2,"cix":2,"bm":0,"ix":1,"mn":"ADBE Vector Group","hd":false},{"ty":"gr","it":[{"ind":0,"ty":"sh","ix":1,"ks":{"a":0,"k":{"i":[[0,0],[10.832,-5.394],[37.243,14.263],[1.858,12.175],[-0.147,2.391],[0,0],[-12.706,11.605],[-0.473,0.417],[2.106,-40.064],[-7.937,14.554],[-5.682,4.543],[-0.513,-15.952],[-2.167,-9.643],[-13.815,20.212],[-6.604,14.312],[-7.827,-15.599],[1.003,-41.928],[11.318,-11.073],[-27.239,-11.557],[-4.025,22.254],[7.265,9.183],[-4.919,21.827],[-8.652,11.589],[-6.506,-16.509],[-5.797,-6.327],[-8.731,19.006],[-3.582,22.237],[-12.276,-16.724],[-4.091,-5.69],[-2.911,10.701],[0.05,14.857],[-20.794,-21.342],[-0.815,-7.922],[7.031,-15.649],[-14.722,-4.825],[2.616,21.679],[5.162,3.456],[1.349,13.279],[0,0],[-3.87,-5.469],[-1.587,-1.751],[0.299,4.423],[-0.008,8.945]],"o":[[0.224,12.101],[-104.684,52.126],[-11.507,-4.407],[-0.326,-2.104],[0,0],[2.623,-17.008],[0.455,-0.416],[-9.251,10.175],[0,0],[0,0],[0,0],[0,0],[0,0],[0,0],[0,0],[0,0],[0,0],[0,0],[0,0],[0,0],[0,0],[0,0],[0,0],[0,0],[0,0],[0,0],[0,0],[0,0],[0,0],[0,0],[0,0],[0,0],[0,0],[0,0],[0,0],[0,0],[0,0],[0,0],[0,0],[0,0],[1.578,1.742],[0,0],[0,0]],"v":[[163.985,42.963],[145.962,70.869],[-140.148,82.684],[-163.636,58.431],[-163.926,51.698],[-147.264,-56.351],[-123.747,-100.696],[-122.355,-101.946],[-145.288,-31.128],[-137.052,-29.501],[-119.867,-59.536],[-108.24,-53.985],[-110.574,-0.431],[-93.902,1.848],[-76.078,-29.302],[-57.482,-30.976],[-51.678,30.999],[-61.512,50.468],[-51.34,84.868],[-28.395,66.701],[-33.623,47.954],[-35.28,18.494],[-22.247,-19.983],[-5.785,-16.858],[9.903,23.205],[28.564,17.979],[36.762,-18.533],[54.884,-21.413],[70.015,5.461],[79.28,2.624],[83.276,-32.924],[105.799,-37.771],[117.28,-16.647],[114.041,0.208],[124.582,18.414],[140.865,-0.289],[134.055,-8.812],[127.102,-25.087],[122.484,-58.704],[126.453,-60.107],[133.751,-49.152],[138.35,-52.121],[138.731,-67.638]],"c":true},"ix":2},"nm":"Path 1","mn":"ADBE Vector Shape - Group","hd":false},{"ty":"fl","c":{"a":0,"k":[0.349019616842,0.129411771894,0.058823529631,1],"ix":4},"o":{"a":0,"k":100,"ix":5},"r":1,"bm":0,"nm":"Fill 1","mn":"ADBE Vector Graphic - Fill","hd":false},{"ty":"tr","p":{"a":0,"k":[302.95,429.712],"ix":2},"a":{"a":0,"k":[0,0],"ix":1},"s":{"a":0,"k":[100,100],"ix":3},"r":{"a":0,"k":0,"ix":6},"o":{"a":0,"k":100,"ix":7},"sk":{"a":0,"k":0,"ix":4},"sa":{"a":0,"k":0,"ix":5},"nm":"Transform"}],"nm":"Group 2","np":2,"cix":2,"bm":0,"ix":2,"mn":"ADBE Vector Group","hd":false}],"ip":0,"op":125,"st":0,"ct":1,"bm":0},{"ddd":0,"ind":14,"ty":4,"nm":"Layer 7","parent":12,"sr":1,"ks":{"o":{"a":0,"k":100,"ix":11},"r":{"a":0,"k":0,"ix":10},"p":{"a":0,"k":[0,0,0],"ix":2,"l":2},"a":{"a":0,"k":[0,0,0],"ix":1,"l":2},"s":{"a":0,"k":[100,100,100],"ix":6,"l":2}},"ao":0,"shapes":[{"ty":"gr","it":[{"ind":0,"ty":"sh","ix":1,"ks":{"a":0,"k":{"i":[[-0.441,-23.768],[56.05,-1.039],[0.441,23.768],[-56.05,1.039]],"o":[[0.441,23.768],[-56.05,1.039],[-0.441,-23.768],[56.05,-1.039]],"v":[[101.488,-1.881],[0.798,43.036],[-101.488,1.881],[-0.798,-43.036]],"c":true},"ix":2},"nm":"Path 1","mn":"ADBE Vector Shape - Group","hd":false},{"ty":"fl","c":{"a":0,"k":[0.996078431606,0.956862747669,0.917647063732,1],"ix":4},"o":{"a":0,"k":100,"ix":5},"r":1,"bm":0,"nm":"Fill 1","mn":"ADBE Vector Graphic - Fill","hd":false},{"ty":"tr","p":{"a":0,"k":[0,0],"ix":2},"a":{"a":0,"k":[0,0],"ix":1},"s":{"a":0,"k":[100,100],"ix":3},"r":{"a":0,"k":0,"ix":6},"o":{"a":0,"k":100,"ix":7},"sk":{"a":0,"k":0,"ix":4},"sa":{"a":0,"k":0,"ix":5},"nm":"Transform"}],"nm":"Group 1","np":2,"cix":2,"bm":0,"ix":1,"mn":"ADBE Vector Group","hd":false}],"ip":0,"op":125,"st":0,"ct":1,"bm":0},{"ddd":0,"ind":15,"ty":4,"nm":"Layer 6","parent":13,"sr":1,"ks":{"o":{"a":0,"k":100,"ix":11},"r":{"a":0,"k":0,"ix":10},"p":{"a":0,"k":[300.83,403.501,0],"ix":2,"l":2},"a":{"a":0,"k":[0,0,0],"ix":1,"l":2},"s":{"a":0,"k":[100,100,100],"ix":6,"l":2}},"ao":0,"shapes":[{"ty":"gr","it":[{"ind":0,"ty":"sh","ix":1,"ks":{"a":0,"k":{"i":[[0,0],[0,0],[0.629,1.454],[0.3,1.069],[0,0],[1.432,-6.351],[0.027,-1.772],[0,0],[0,0],[0,0],[0,0],[0,0],[0,0],[0,0],[0,0],[0,0],[0,0],[0,0],[4.762,-2.119],[5.174,3.317],[-3.065,6.425],[-1.733,1.876],[0,0],[0,0],[0,0],[0,0],[0,0],[0,0],[0,0],[0,0],[0,0],[-9.251,10.175],[-4.52,3.045],[0,0],[-58.785,-3.444],[-36.48,-30.36],[-5.822,-27.386],[0,0],[0,0],[1.578,1.742],[0,0],[0,0],[0,0],[0,0],[-0.051,-0.035],[1.53,-6.53]],"o":[[-14.722,-4.825],[4.771,-10.619],[-0.441,-1.019],[-2.227,-7.934],[-15.681,-16.094],[-0.39,1.729],[-0.224,14.696],[-2.911,10.701],[-4.091,-5.69],[-12.276,-16.724],[-3.582,22.237],[-8.731,19.006],[-5.797,-6.327],[-6.506,-16.509],[-8.652,11.589],[-4.919,21.827],[7.265,9.183],[-1.811,10.014],[-5.615,2.498],[-13.249,-8.494],[1.099,-2.305],[9.388,-10.161],[1.003,-41.928],[-7.827,-15.599],[-6.604,14.312],[-13.815,20.212],[-2.167,-9.643],[-0.513,-15.952],[-5.682,4.543],[-7.937,14.554],[2.106,-40.064],[3.478,-3.069],[0.017,-0.009],[23.098,-15.538],[0,0],[0,0],[0,0],[-0.008,8.945],[0.299,4.423],[-1.587,-1.751],[-3.87,-5.469],[0,0],[1.349,13.279],[0.052,0.035],[5.533,3.79],[-2.807,11.978]],"v":[[126.702,44.624],[116.161,26.418],[120.09,10.377],[118.942,7.261],[107.919,-11.56],[85.967,-10.368],[85.386,-5.101],[81.4,28.834],[72.135,31.672],[57.004,4.798],[38.882,7.678],[30.684,44.19],[12.023,49.416],[-3.664,9.352],[-20.126,6.227],[-33.16,44.704],[-31.503,74.164],[-26.275,92.912],[-37.676,109.725],[-54.961,108.091],[-61.97,81.113],[-57.622,74.859],[-49.558,57.209],[-55.361,-4.765],[-73.958,-3.092],[-91.782,28.058],[-108.454,25.779],[-106.12,-27.775],[-117.747,-33.325],[-134.932,-3.29],[-143.168,-4.918],[-120.235,-75.735],[-108.257,-84.963],[-108.231,-84.972],[10.967,-110.645],[118.846,-79.837],[140.36,-43.572],[140.851,-41.427],[140.47,-25.91],[135.871,-22.942],[128.573,-33.896],[124.604,-32.494],[129.222,1.123],[136.175,17.398],[136.329,17.502],[142.713,34.726]],"c":true},"ix":2},"nm":"Path 1","mn":"ADBE Vector Shape - Group","hd":false},{"ty":"st","c":{"a":0,"k":[0,0,0,1],"ix":3},"o":{"a":0,"k":100,"ix":4},"w":{"a":0,"k":7,"ix":5},"lc":2,"lj":2,"bm":0,"nm":"Stroke 1","mn":"ADBE Vector Graphic - Stroke","hd":false},{"ty":"tr","p":{"a":0,"k":[0,0],"ix":2},"a":{"a":0,"k":[0,0],"ix":1},"s":{"a":0,"k":[100,100],"ix":3},"r":{"a":0,"k":0,"ix":6},"o":{"a":0,"k":100,"ix":7},"sk":{"a":0,"k":0,"ix":4},"sa":{"a":0,"k":0,"ix":5},"nm":"Transform"}],"nm":"Group 1","np":2,"cix":2,"bm":0,"ix":1,"mn":"ADBE Vector Group","hd":false}],"ip":0,"op":125,"st":0,"ct":1,"bm":0},{"ddd":0,"ind":16,"ty":4,"nm":"Layer 3","parent":13,"sr":1,"ks":{"o":{"a":0,"k":100,"ix":11},"r":{"a":0,"k":0,"ix":10},"p":{"a":0,"k":[302.078,294.977,0],"ix":2,"l":2},"a":{"a":0,"k":[1.247,-108.524,0],"ix":1,"l":2},"s":{"a":1,"k":[{"i":{"x":[0.667,0.667,0.667],"y":[1,1,1]},"o":{"x":[0.333,0.333,0.333],"y":[0,0,0]},"t":10,"s":[100,100,100]},{"i":{"x":[0.667,0.667,0.667],"y":[1,1,1]},"o":{"x":[0.333,0.333,0.333],"y":[0,0,0]},"t":23,"s":[62,31,100]},{"i":{"x":[0.833,0.833,0.833],"y":[1,1,1]},"o":{"x":[0.167,0.167,0.167],"y":[0,0,0]},"t":35,"s":[100,100,100]},{"i":{"x":[0.667,0.667,0.667],"y":[1,1,1]},"o":{"x":[0.167,0.167,0.167],"y":[0,0,0]},"t":45,"s":[95,84,100]},{"t":55,"s":[100,100,100]}],"ix":6,"l":2}},"ao":0,"shapes":[{"ty":"gr","it":[{"ind":0,"ty":"sh","ix":1,"ks":{"a":0,"k":{"i":[[0,0],[0,0],[0.629,1.454],[0.3,1.069],[0,0],[1.432,-6.351],[0.027,-1.772],[0,0],[0,0],[0,0],[0,0],[0,0],[0,0],[0,0],[0,0],[0,0],[0,0],[0,0],[4.762,-2.119],[5.174,3.317],[-3.065,6.425],[-1.733,1.876],[0,0],[0,0],[0,0],[0,0],[0,0],[0,0],[0,0],[0,0],[0,0],[-9.251,10.175],[-4.52,3.045],[0,0],[-58.785,-3.444],[-36.48,-30.36],[-5.822,-27.386],[0,0],[0,0],[1.578,1.742],[0,0],[0,0],[0,0],[0,0],[-0.051,-0.035],[1.53,-6.53]],"o":[[-14.722,-4.825],[4.771,-10.619],[-0.441,-1.019],[-2.227,-7.934],[-15.681,-16.094],[-0.39,1.729],[-0.224,14.696],[-2.911,10.701],[-4.091,-5.69],[-12.276,-16.724],[-3.582,22.237],[-8.731,19.006],[-5.797,-6.327],[-6.506,-16.509],[-8.652,11.589],[-4.919,21.827],[7.265,9.183],[-1.811,10.014],[-5.615,2.498],[-13.249,-8.494],[1.099,-2.305],[9.388,-10.161],[1.003,-41.928],[-7.827,-15.599],[-6.604,14.312],[-13.815,20.212],[-2.167,-9.643],[-0.513,-15.952],[-5.682,4.543],[-7.937,14.554],[2.106,-40.064],[3.478,-3.069],[0.017,-0.009],[23.098,-15.538],[0,0],[0,0],[0,0],[-0.008,8.945],[0.299,4.423],[-1.587,-1.751],[-3.87,-5.469],[0,0],[1.349,13.279],[0.052,0.035],[5.533,3.79],[-2.807,11.978]],"v":[[126.702,44.624],[116.161,26.418],[120.09,10.377],[118.942,7.261],[107.919,-11.56],[85.967,-10.368],[85.386,-5.101],[81.4,28.834],[72.135,31.672],[57.004,4.798],[38.882,7.678],[30.684,44.19],[12.023,49.416],[-3.664,9.352],[-20.126,6.227],[-33.16,44.704],[-31.503,74.164],[-26.275,92.912],[-37.676,109.725],[-54.961,108.091],[-61.97,81.113],[-57.622,74.859],[-49.558,57.209],[-55.361,-4.765],[-73.958,-3.092],[-91.782,28.058],[-108.454,25.779],[-106.12,-27.775],[-117.747,-33.325],[-134.932,-3.29],[-143.168,-4.918],[-120.235,-75.735],[-108.257,-84.963],[-108.231,-84.972],[10.967,-110.645],[118.846,-79.837],[140.36,-43.572],[140.851,-41.427],[140.47,-25.91],[135.871,-22.942],[128.573,-33.896],[124.604,-32.494],[129.222,1.123],[136.175,17.398],[136.329,17.502],[142.713,34.726]],"c":true},"ix":2},"nm":"Path 1","mn":"ADBE Vector Shape - Group","hd":false},{"ty":"fl","c":{"a":0,"k":[0.850980401039,0.72549021244,0.560784339905,1],"ix":4},"o":{"a":0,"k":100,"ix":5},"r":1,"bm":0,"nm":"Fill 1","mn":"ADBE Vector Graphic - Fill","hd":false},{"ty":"tr","p":{"a":0,"k":[0,0],"ix":2},"a":{"a":0,"k":[0,0],"ix":1},"s":{"a":0,"k":[100,100],"ix":3},"r":{"a":0,"k":0,"ix":6},"o":{"a":0,"k":100,"ix":7},"sk":{"a":0,"k":0,"ix":4},"sa":{"a":0,"k":0,"ix":5},"nm":"Transform"}],"nm":"Group 1","np":2,"cix":2,"bm":0,"ix":1,"mn":"ADBE Vector Group","hd":false}],"ip":0,"op":125,"st":0,"ct":1,"bm":0},{"ddd":0,"ind":17,"ty":4,"nm":"Layer 17","parent":13,"sr":1,"ks":{"o":{"a":0,"k":100,"ix":11},"r":{"a":0,"k":0,"ix":10},"p":{"a":0,"k":[300.83,415.308,0],"ix":2,"l":2},"a":{"a":0,"k":[0,0,0],"ix":1,"l":2},"s":{"a":0,"k":[100,91.072,100],"ix":6,"l":2}},"ao":0,"shapes":[{"ty":"gr","it":[{"ind":0,"ty":"sh","ix":1,"ks":{"a":0,"k":{"i":[[0,0],[0,0],[0.629,1.454],[0.3,1.069],[0,0],[1.432,-6.351],[0.027,-1.772],[0,0],[0,0],[0,0],[0,0],[0,0],[0,0],[0,0],[0,0],[0,0],[0,0],[0,0],[4.762,-2.119],[5.174,3.317],[-3.065,6.425],[-1.733,1.876],[0,0],[0,0],[0,0],[0,0],[0,0],[0,0],[0,0],[0,0],[0,0],[-9.251,10.175],[-4.52,3.045],[0,0],[-58.785,-3.444],[-36.48,-30.36],[-5.822,-27.386],[0,0],[0,0],[1.578,1.742],[0,0],[0,0],[0,0],[0,0],[-0.051,-0.035],[1.53,-6.53]],"o":[[-14.722,-4.825],[4.771,-10.619],[-0.441,-1.019],[-2.227,-7.934],[-15.681,-16.094],[-0.39,1.729],[-0.224,14.696],[-2.911,10.701],[-4.091,-5.69],[-12.276,-16.724],[-3.582,22.237],[-8.731,19.006],[-5.797,-6.327],[-6.506,-16.509],[-8.652,11.589],[-4.919,21.827],[7.265,9.183],[-1.811,10.014],[-5.615,2.498],[-13.249,-8.494],[1.099,-2.305],[9.388,-10.161],[1.003,-41.928],[-7.827,-15.599],[-6.604,14.312],[-13.815,20.212],[-2.167,-9.643],[-0.513,-15.952],[-5.682,4.543],[-7.937,14.554],[2.106,-40.064],[3.478,-3.069],[0.017,-0.009],[23.098,-15.538],[0,0],[0,0],[0,0],[-0.008,8.945],[0.299,4.423],[-1.587,-1.751],[-3.87,-5.469],[0,0],[1.349,13.279],[0.052,0.035],[5.533,3.79],[-2.807,11.978]],"v":[[126.702,44.624],[116.161,26.418],[120.09,10.377],[118.942,7.261],[107.919,-11.56],[85.967,-10.368],[85.386,-5.101],[81.4,28.834],[72.135,31.672],[57.004,4.798],[38.882,7.678],[30.684,44.19],[12.023,49.416],[-3.664,9.352],[-20.126,6.227],[-33.16,44.704],[-31.503,74.164],[-26.275,92.912],[-37.676,109.725],[-54.961,108.091],[-61.97,81.113],[-57.622,74.859],[-49.558,57.209],[-55.361,-4.765],[-73.958,-3.092],[-91.782,28.058],[-108.454,25.779],[-106.12,-27.775],[-117.747,-33.325],[-134.932,-3.29],[-143.168,-4.918],[-120.235,-75.735],[-108.257,-84.963],[-108.231,-84.972],[10.967,-110.645],[118.846,-79.837],[140.36,-43.572],[140.851,-41.427],[140.47,-25.91],[135.871,-22.942],[128.573,-33.896],[124.604,-32.494],[129.222,1.123],[136.175,17.398],[136.329,17.502],[142.713,34.726]],"c":true},"ix":2},"nm":"Path 1","mn":"ADBE Vector Shape - Group","hd":false},{"ty":"fl","c":{"a":0,"k":[0.996078431606,0.956862747669,0.917647063732,1],"ix":4},"o":{"a":0,"k":100,"ix":5},"r":1,"bm":0,"nm":"Fill 1","mn":"ADBE Vector Graphic - Fill","hd":false},{"ty":"tr","p":{"a":0,"k":[0,0],"ix":2},"a":{"a":0,"k":[0,0],"ix":1},"s":{"a":0,"k":[100,100],"ix":3},"r":{"a":0,"k":0,"ix":6},"o":{"a":0,"k":100,"ix":7},"sk":{"a":0,"k":0,"ix":4},"sa":{"a":0,"k":0,"ix":5},"nm":"Transform"}],"nm":"Group 1","np":2,"cix":2,"bm":0,"ix":1,"mn":"ADBE Vector Group","hd":false}],"ip":0,"op":125,"st":0,"ct":1,"bm":0},{"ddd":0,"ind":18,"ty":4,"nm":"Layer 5","parent":13,"sr":1,"ks":{"o":{"a":0,"k":100,"ix":11},"r":{"a":0,"k":0,"ix":10},"p":{"a":0,"k":[299.917,339.08,0],"ix":2,"l":2},"a":{"a":0,"k":[0,0,0],"ix":1,"l":2},"s":{"a":0,"k":[100,100,100],"ix":6,"l":2}},"ao":0,"shapes":[{"ty":"gr","it":[{"ind":0,"ty":"sh","ix":1,"ks":{"a":0,"k":{"i":[[-0.441,-23.768],[56.05,-1.039],[0.441,23.768],[-56.05,1.039]],"o":[[0.441,23.768],[-56.05,1.039],[-0.441,-23.768],[56.05,-1.039]],"v":[[101.488,-1.881],[0.798,43.036],[-101.488,1.881],[-0.798,-43.036]],"c":true},"ix":2},"nm":"Path 1","mn":"ADBE Vector Shape - Group","hd":false},{"ty":"fl","c":{"a":0,"k":[0.996078431606,0.956862747669,0.917647063732,1],"ix":4},"o":{"a":0,"k":100,"ix":5},"r":1,"bm":0,"nm":"Fill 1","mn":"ADBE Vector Graphic - Fill","hd":false},{"ty":"tr","p":{"a":0,"k":[0,0],"ix":2},"a":{"a":0,"k":[0,0],"ix":1},"s":{"a":0,"k":[100,100],"ix":3},"r":{"a":0,"k":0,"ix":6},"o":{"a":0,"k":100,"ix":7},"sk":{"a":0,"k":0,"ix":4},"sa":{"a":0,"k":0,"ix":5},"nm":"Transform"}],"nm":"Group 1","np":2,"cix":2,"bm":0,"ix":1,"mn":"ADBE Vector Group","hd":false}],"ip":0,"op":125,"st":0,"ct":1,"bm":0},{"ddd":0,"ind":19,"ty":4,"nm":"Layer 4","parent":13,"sr":1,"ks":{"o":{"a":0,"k":100,"ix":11},"r":{"a":0,"k":0,"ix":10},"p":{"a":0,"k":[299.983,457.151,0],"ix":2,"l":2},"a":{"a":0,"k":[299.983,457.151,0],"ix":1,"l":2},"s":{"a":0,"k":[100,100,100],"ix":6,"l":2}},"ao":0,"shapes":[{"ty":"gr","it":[{"ind":0,"ty":"sh","ix":1,"ks":{"a":0,"k":{"i":[[2.122,0],[0,2.46],[-2.122,0],[0,-2.46]],"o":[[-2.122,0],[0,-2.46],[2.122,0],[0,2.46]],"v":[[0,4.454],[-3.843,0],[0,-4.454],[3.843,0]],"c":true},"ix":2},"nm":"Path 1","mn":"ADBE Vector Shape - Group","hd":false},{"ty":"fl","c":{"a":0,"k":[1,0.772549033165,0.768627464771,1],"ix":4},"o":{"a":0,"k":100,"ix":5},"r":1,"bm":0,"nm":"Fill 1","mn":"ADBE Vector Graphic - Fill","hd":false},{"ty":"tr","p":{"a":0,"k":[357.583,443.106],"ix":2},"a":{"a":0,"k":[0,0],"ix":1},"s":{"a":0,"k":[100,100],"ix":3},"r":{"a":0,"k":0,"ix":6},"o":{"a":0,"k":50,"ix":7},"sk":{"a":0,"k":0,"ix":4},"sa":{"a":0,"k":0,"ix":5},"nm":"Transform"}],"nm":"Group 1","np":2,"cix":2,"bm":0,"ix":1,"mn":"ADBE Vector Group","hd":false},{"ty":"gr","it":[{"ind":0,"ty":"sh","ix":1,"ks":{"a":0,"k":{"i":[[5.608,0],[0,6.498],[-5.608,0],[0,-6.498]],"o":[[-5.608,0],[0,-6.498],[5.608,0],[0,6.498]],"v":[[0,11.766],[-10.153,0],[0,-11.766],[10.153,0]],"c":true},"ix":2},"nm":"Path 1","mn":"ADBE Vector Shape - Group","hd":false},{"ty":"fl","c":{"a":0,"k":[0.600000023842,0.105882354081,0.113725490868,1],"ix":4},"o":{"a":0,"k":100,"ix":5},"r":1,"bm":0,"nm":"Fill 1","mn":"ADBE Vector Graphic - Fill","hd":false},{"ty":"tr","p":{"a":0,"k":[209.41,494.17],"ix":2},"a":{"a":0,"k":[0,0],"ix":1},"s":{"a":0,"k":[100,100],"ix":3},"r":{"a":0,"k":0,"ix":6},"o":{"a":0,"k":50,"ix":7},"sk":{"a":0,"k":0,"ix":4},"sa":{"a":0,"k":0,"ix":5},"nm":"Transform"}],"nm":"Group 2","np":2,"cix":2,"bm":0,"ix":2,"mn":"ADBE Vector Group","hd":false},{"ty":"gr","it":[{"ind":0,"ty":"sh","ix":1,"ks":{"a":0,"k":{"i":[[2.384,0],[0,2.763],[-2.384,0],[0,-2.763]],"o":[[-2.384,0],[0,-2.763],[2.384,0],[0,2.763]],"v":[[0,5.003],[-4.317,0],[0,-5.003],[4.317,0]],"c":true},"ix":2},"nm":"Path 1","mn":"ADBE Vector Shape - Group","hd":false},{"ty":"fl","c":{"a":0,"k":[0.831372559071,0.188235297799,0.188235297799,1],"ix":4},"o":{"a":0,"k":100,"ix":5},"r":1,"bm":0,"nm":"Fill 1","mn":"ADBE Vector Graphic - Fill","hd":false},{"ty":"tr","p":{"a":0,"k":[361.426,499.043],"ix":2},"a":{"a":0,"k":[0,0],"ix":1},"s":{"a":0,"k":[100,100],"ix":3},"r":{"a":0,"k":0,"ix":6},"o":{"a":0,"k":66,"ix":7},"sk":{"a":0,"k":0,"ix":4},"sa":{"a":0,"k":0,"ix":5},"nm":"Transform"}],"nm":"Group 3","np":2,"cix":2,"bm":0,"ix":3,"mn":"ADBE Vector Group","hd":false},{"ty":"gr","it":[{"ind":0,"ty":"sh","ix":1,"ks":{"a":0,"k":{"i":[[3.285,0],[0,3.807],[-3.285,0],[0,-3.807]],"o":[[-3.285,0],[0,-3.807],[3.285,0],[0,3.807]],"v":[[0,6.894],[-5.949,0],[0,-6.894],[5.949,0]],"c":true},"ix":2},"nm":"Path 1","mn":"ADBE Vector Shape - Group","hd":false},{"ty":"fl","c":{"a":0,"k":[0.89411765337,0.050980392843,0.043137256056,1],"ix":4},"o":{"a":0,"k":100,"ix":5},"r":1,"bm":0,"nm":"Fill 1","mn":"ADBE Vector Graphic - Fill","hd":false},{"ty":"tr","p":{"a":0,"k":[434.957,482.403],"ix":2},"a":{"a":0,"k":[0,0],"ix":1},"s":{"a":0,"k":[100,100],"ix":3},"r":{"a":0,"k":0,"ix":6},"o":{"a":0,"k":47,"ix":7},"sk":{"a":0,"k":0,"ix":4},"sa":{"a":0,"k":0,"ix":5},"nm":"Transform"}],"nm":"Group 4","np":2,"cix":2,"bm":0,"ix":4,"mn":"ADBE Vector Group","hd":false},{"ty":"gr","it":[{"ind":0,"ty":"sh","ix":1,"ks":{"a":0,"k":{"i":[[3.285,0],[0,3.807],[-3.285,0],[0,-3.807]],"o":[[-3.285,0],[0,-3.807],[3.285,0],[0,3.807]],"v":[[0,6.894],[-5.949,0],[0,-6.894],[5.949,0]],"c":true},"ix":2},"nm":"Path 1","mn":"ADBE Vector Shape - Group","hd":false},{"ty":"fl","c":{"a":0,"k":[0.980392158031,0.501960813999,0.113725490868,1],"ix":4},"o":{"a":0,"k":100,"ix":5},"r":1,"bm":0,"nm":"Fill 1","mn":"ADBE Vector Graphic - Fill","hd":false},{"ty":"tr","p":{"a":0,"k":[292.133,467.106],"ix":2},"a":{"a":0,"k":[0,0],"ix":1},"s":{"a":0,"k":[100,100],"ix":3},"r":{"a":0,"k":0,"ix":6},"o":{"a":0,"k":60,"ix":7},"sk":{"a":0,"k":0,"ix":4},"sa":{"a":0,"k":0,"ix":5},"nm":"Transform"}],"nm":"Group 5","np":2,"cix":2,"bm":0,"ix":5,"mn":"ADBE Vector Group","hd":false},{"ty":"gr","it":[{"ind":0,"ty":"sh","ix":1,"ks":{"a":0,"k":{"i":[[3.285,0],[0,3.807],[-3.285,0],[0,-3.807]],"o":[[-3.285,0],[0,-3.807],[3.285,0],[0,3.807]],"v":[[0,6.894],[-5.949,0],[0,-6.894],[5.949,0]],"c":true},"ix":2},"nm":"Path 1","mn":"ADBE Vector Shape - Group","hd":false},{"ty":"fl","c":{"a":0,"k":[1,0.941176474094,0.945098042488,1],"ix":4},"o":{"a":0,"k":100,"ix":5},"r":1,"bm":0,"nm":"Fill 1","mn":"ADBE Vector Graphic - Fill","hd":false},{"ty":"tr","p":{"a":0,"k":[165.009,444.894],"ix":2},"a":{"a":0,"k":[0,0],"ix":1},"s":{"a":0,"k":[100,100],"ix":3},"r":{"a":0,"k":0,"ix":6},"o":{"a":0,"k":87,"ix":7},"sk":{"a":0,"k":0,"ix":4},"sa":{"a":0,"k":0,"ix":5},"nm":"Transform"}],"nm":"Group 6","np":2,"cix":2,"bm":0,"ix":6,"mn":"ADBE Vector Group","hd":false},{"ty":"gr","it":[{"ind":0,"ty":"sh","ix":1,"ks":{"a":0,"k":{"i":[[0,-1.533],[2.266,0],[0,1.533],[-2.266,0]],"o":[[0,1.533],[-2.266,0],[0,-1.533],[2.266,0]],"v":[[4.102,0],[0,2.776],[-4.102,0],[0,-2.776]],"c":true},"ix":2},"nm":"Path 1","mn":"ADBE Vector Shape - Group","hd":false},{"ty":"fl","c":{"a":0,"k":[0.215686276555,0.32549020648,0.156862750649,1],"ix":4},"o":{"a":0,"k":100,"ix":5},"r":1,"bm":0,"nm":"Fill 1","mn":"ADBE Vector Graphic - Fill","hd":false},{"ty":"tr","p":{"a":0,"k":[179.097,411.143],"ix":2},"a":{"a":0,"k":[0,0],"ix":1},"s":{"a":0,"k":[100,100],"ix":3},"r":{"a":0,"k":0,"ix":6},"o":{"a":0,"k":100,"ix":7},"sk":{"a":0,"k":0,"ix":4},"sa":{"a":0,"k":0,"ix":5},"nm":"Transform"}],"nm":"Group 7","np":2,"cix":2,"bm":0,"ix":7,"mn":"ADBE Vector Group","hd":false},{"ty":"gr","it":[{"ind":0,"ty":"sh","ix":1,"ks":{"a":0,"k":{"i":[[0,-2.577],[3.807,0],[0,2.577],[-3.807,0]],"o":[[0,2.577],[-3.807,0],[0,-2.577],[3.807,0]],"v":[[6.894,0],[0,4.665],[-6.894,0],[0,-4.665]],"c":true},"ix":2},"nm":"Path 1","mn":"ADBE Vector Shape - Group","hd":false},{"ty":"fl","c":{"a":0,"k":[1,0.941176474094,0.945098042488,1],"ix":4},"o":{"a":0,"k":100,"ix":5},"r":1,"bm":0,"nm":"Fill 1","mn":"ADBE Vector Graphic - Fill","hd":false},{"ty":"tr","p":{"a":0,"k":[238.106,434.377],"ix":2},"a":{"a":0,"k":[0,0],"ix":1},"s":{"a":0,"k":[100,100],"ix":3},"r":{"a":0,"k":0,"ix":6},"o":{"a":0,"k":54,"ix":7},"sk":{"a":0,"k":0,"ix":4},"sa":{"a":0,"k":0,"ix":5},"nm":"Transform"}],"nm":"Group 8","np":2,"cix":2,"bm":0,"ix":8,"mn":"ADBE Vector Group","hd":false}],"ip":0,"op":125,"st":0,"ct":1,"bm":0},{"ddd":0,"ind":20,"ty":4,"nm":"Layer 10","parent":22,"sr":1,"ks":{"o":{"a":0,"k":100,"ix":11},"r":{"a":0,"k":0,"ix":10},"p":{"a":0,"k":[46.567,53.854,0],"ix":2,"l":2},"a":{"a":0,"k":[253.686,322.386,0],"ix":1,"l":2},"s":{"a":0,"k":[100,100,100],"ix":6,"l":2}},"ao":0,"shapes":[{"ty":"gr","it":[{"ind":0,"ty":"sh","ix":1,"ks":{"a":0,"k":{"i":[[0,0],[0,0]],"o":[[0,0],[0,0]],"v":[[16.286,2.515],[-16.286,-2.515]],"c":false},"ix":2},"nm":"Path 1","mn":"ADBE Vector Shape - Group","hd":false},{"ty":"st","c":{"a":0,"k":[0.215686276555,0.32549020648,0.156862750649,1],"ix":3},"o":{"a":0,"k":100,"ix":4},"w":{"a":0,"k":5,"ix":5},"lc":2,"lj":2,"bm":0,"nm":"Stroke 1","mn":"ADBE Vector Graphic - Stroke","hd":false},{"ty":"tr","p":{"a":0,"k":[186.279,264.653],"ix":2},"a":{"a":0,"k":[0,0],"ix":1},"s":{"a":0,"k":[100,100],"ix":3},"r":{"a":0,"k":0,"ix":6},"o":{"a":0,"k":100,"ix":7},"sk":{"a":0,"k":0,"ix":4},"sa":{"a":0,"k":0,"ix":5},"nm":"Transform"}],"nm":"Group 1","np":2,"cix":2,"bm":0,"ix":1,"mn":"ADBE Vector Group","hd":false},{"ty":"gr","it":[{"ind":0,"ty":"sh","ix":1,"ks":{"a":0,"k":{"i":[[0,0],[0,0]],"o":[[0,0],[0,0]],"v":[[-2.037,13.187],[2.037,-13.187]],"c":false},"ix":2},"nm":"Path 1","mn":"ADBE Vector Shape - Group","hd":false},{"ty":"st","c":{"a":0,"k":[0.215686276555,0.32549020648,0.156862750649,1],"ix":3},"o":{"a":0,"k":100,"ix":4},"w":{"a":0,"k":5,"ix":5},"lc":2,"lj":2,"bm":0,"nm":"Stroke 1","mn":"ADBE Vector Graphic - Stroke","hd":false},{"ty":"tr","p":{"a":0,"k":[215.036,261.686],"ix":2},"a":{"a":0,"k":[0,0],"ix":1},"s":{"a":0,"k":[100,100],"ix":3},"r":{"a":0,"k":0,"ix":6},"o":{"a":0,"k":100,"ix":7},"sk":{"a":0,"k":0,"ix":4},"sa":{"a":0,"k":0,"ix":5},"nm":"Transform"}],"nm":"Group 2","np":2,"cix":2,"bm":0,"ix":2,"mn":"ADBE Vector Group","hd":false},{"ty":"gr","it":[{"ind":0,"ty":"sh","ix":1,"ks":{"a":0,"k":{"i":[[0,0],[0,0],[0,0]],"o":[[0,0],[0,0],[0,0]],"v":[[14.885,-13.311],[10.773,13.311],[-14.885,11.719]],"c":false},"ix":2},"nm":"Path 1","mn":"ADBE Vector Shape - Group","hd":false},{"ty":"st","c":{"a":0,"k":[0.215686276555,0.32549020648,0.156862750649,1],"ix":3},"o":{"a":0,"k":100,"ix":4},"w":{"a":0,"k":5,"ix":5},"lc":2,"lj":2,"bm":0,"nm":"Stroke 1","mn":"ADBE Vector Graphic - Stroke","hd":false},{"ty":"tr","p":{"a":0,"k":[221.292,283.79],"ix":2},"a":{"a":0,"k":[0,0],"ix":1},"s":{"a":0,"k":[100,100],"ix":3},"r":{"a":0,"k":0,"ix":6},"o":{"a":0,"k":100,"ix":7},"sk":{"a":0,"k":0,"ix":4},"sa":{"a":0,"k":0,"ix":5},"nm":"Transform"}],"nm":"Group 3","np":2,"cix":2,"bm":0,"ix":3,"mn":"ADBE Vector Group","hd":false},{"ty":"gr","it":[{"ind":0,"ty":"sh","ix":1,"ks":{"a":0,"k":{"i":[[0,0],[0,0]],"o":[[0,0],[0,0]],"v":[[34.535,36.635],[-34.535,-36.635]],"c":false},"ix":2},"nm":"Path 1","mn":"ADBE Vector Shape - Group","hd":false},{"ty":"st","c":{"a":0,"k":[0.215686276555,0.32549020648,0.156862750649,1],"ix":3},"o":{"a":0,"k":100,"ix":4},"w":{"a":0,"k":5,"ix":5},"lc":2,"lj":2,"bm":0,"nm":"Stroke 1","mn":"ADBE Vector Graphic - Stroke","hd":false},{"ty":"tr","p":{"a":0,"k":[215.526,278.727],"ix":2},"a":{"a":0,"k":[0,0],"ix":1},"s":{"a":0,"k":[100,100],"ix":3},"r":{"a":0,"k":0,"ix":6},"o":{"a":0,"k":100,"ix":7},"sk":{"a":0,"k":0,"ix":4},"sa":{"a":0,"k":0,"ix":5},"nm":"Transform"}],"nm":"Group 4","np":2,"cix":2,"bm":0,"ix":4,"mn":"ADBE Vector Group","hd":false}],"ip":0,"op":125,"st":0,"ct":1,"bm":0},{"ddd":0,"ind":21,"ty":4,"nm":"leaf 1","parent":13,"sr":1,"ks":{"o":{"a":0,"k":100,"ix":11},"r":{"a":1,"k":[{"i":{"x":[0.667],"y":[1]},"o":{"x":[0.333],"y":[0]},"t":35,"s":[0]},{"i":{"x":[0.667],"y":[1]},"o":{"x":[0.333],"y":[0]},"t":45,"s":[-10]},{"i":{"x":[0.667],"y":[1]},"o":{"x":[0.333],"y":[0]},"t":55,"s":[10]},{"i":{"x":[0.667],"y":[1]},"o":{"x":[0.333],"y":[0]},"t":65,"s":[-5]},{"t":75,"s":[0]}],"ix":10},"p":{"a":0,"k":[339.917,324.948,0],"ix":2,"l":2},"a":{"a":0,"k":[39.917,24.948,0],"ix":1,"l":2},"s":{"a":1,"k":[{"i":{"x":[0.667,0.667,0.667],"y":[1,1,1]},"o":{"x":[0.333,0.333,0.333],"y":[0,0,0]},"t":23,"s":[0,0,100]},{"i":{"x":[0.667,0.667,0.667],"y":[1,1,1]},"o":{"x":[0.333,0.333,0.333],"y":[0,0,0]},"t":29,"s":[110,110,100]},{"t":35,"s":[100,100,100]}],"ix":6,"l":2}},"ao":0,"shapes":[{"ty":"gr","it":[{"ty":"gr","it":[{"ind":0,"ty":"sh","ix":1,"ks":{"a":0,"k":{"i":[[0,0],[0,0]],"o":[[0,0],[0,0]],"v":[[98.194,-34.437],[130.765,-39.468]],"c":false},"ix":2},"nm":"Path 1","mn":"ADBE Vector Shape - Group","hd":false},{"ty":"st","c":{"a":0,"k":[0.215686276555,0.32549020648,0.156862750649,1],"ix":3},"o":{"a":0,"k":100,"ix":4},"w":{"a":0,"k":5,"ix":5},"lc":2,"lj":2,"bm":0,"nm":"Stroke 1","mn":"ADBE Vector Graphic - Stroke","hd":false},{"ty":"tr","p":{"a":0,"k":[0,0],"ix":2},"a":{"a":0,"k":[0,0],"ix":1},"s":{"a":0,"k":[100,100],"ix":3},"r":{"a":0,"k":0,"ix":6},"o":{"a":0,"k":100,"ix":7},"sk":{"a":0,"k":0,"ix":4},"sa":{"a":0,"k":0,"ix":5},"nm":"Transform"}],"nm":"Group 1","np":2,"cix":2,"bm":0,"ix":1,"mn":"ADBE Vector Group","hd":false},{"ty":"gr","it":[{"ind":0,"ty":"sh","ix":1,"ks":{"a":0,"k":{"i":[[0,0],[0,0]],"o":[[0,0],[0,0]],"v":[[87.76,-26.731],[83.687,-53.105]],"c":false},"ix":2},"nm":"Path 1","mn":"ADBE Vector Shape - Group","hd":false},{"ty":"st","c":{"a":0,"k":[0.215686276555,0.32549020648,0.156862750649,1],"ix":3},"o":{"a":0,"k":100,"ix":4},"w":{"a":0,"k":5,"ix":5},"lc":2,"lj":2,"bm":0,"nm":"Stroke 1","mn":"ADBE Vector Graphic - Stroke","hd":false},{"ty":"tr","p":{"a":0,"k":[0,0],"ix":2},"a":{"a":0,"k":[0,0],"ix":1},"s":{"a":0,"k":[100,100],"ix":3},"r":{"a":0,"k":0,"ix":6},"o":{"a":0,"k":100,"ix":7},"sk":{"a":0,"k":0,"ix":4},"sa":{"a":0,"k":0,"ix":5},"nm":"Transform"}],"nm":"Group 2","np":2,"cix":2,"bm":0,"ix":2,"mn":"ADBE Vector Group","hd":false},{"ty":"gr","it":[{"ind":0,"ty":"sh","ix":1,"ks":{"a":0,"k":{"i":[[0,0],[0,0],[0,0]],"o":[[0,0],[0,0],[0,0]],"v":[[64.583,-31.126],[68.694,-4.503],[94.352,-6.095]],"c":false},"ix":2},"nm":"Path 1","mn":"ADBE Vector Shape - Group","hd":false},{"ty":"st","c":{"a":0,"k":[0.215686276555,0.32549020648,0.156862750649,1],"ix":3},"o":{"a":0,"k":100,"ix":4},"w":{"a":0,"k":5,"ix":5},"lc":2,"lj":2,"bm":0,"nm":"Stroke 1","mn":"ADBE Vector Graphic - Stroke","hd":false},{"ty":"tr","p":{"a":0,"k":[0,0],"ix":2},"a":{"a":0,"k":[0,0],"ix":1},"s":{"a":0,"k":[100,100],"ix":3},"r":{"a":0,"k":0,"ix":6},"o":{"a":0,"k":100,"ix":7},"sk":{"a":0,"k":0,"ix":4},"sa":{"a":0,"k":0,"ix":5},"nm":"Transform"}],"nm":"Group 3","np":2,"cix":2,"bm":0,"ix":3,"mn":"ADBE Vector Group","hd":false},{"ty":"gr","it":[{"ind":0,"ty":"sh","ix":1,"ks":{"a":0,"k":{"i":[[0,0],[0,0]],"o":[[0,0],[0,0]],"v":[[50.698,13.758],[119.768,-59.512]],"c":false},"ix":2},"nm":"Path 1","mn":"ADBE Vector Shape - Group","hd":false},{"ty":"st","c":{"a":0,"k":[0.215686276555,0.32549020648,0.156862750649,1],"ix":3},"o":{"a":0,"k":100,"ix":4},"w":{"a":0,"k":5,"ix":5},"lc":2,"lj":2,"bm":0,"nm":"Stroke 1","mn":"ADBE Vector Graphic - Stroke","hd":false},{"ty":"tr","p":{"a":0,"k":[0,0],"ix":2},"a":{"a":0,"k":[0,0],"ix":1},"s":{"a":0,"k":[100,100],"ix":3},"r":{"a":0,"k":0,"ix":6},"o":{"a":0,"k":100,"ix":7},"sk":{"a":0,"k":0,"ix":4},"sa":{"a":0,"k":0,"ix":5},"nm":"Transform"}],"nm":"Group 4","np":2,"cix":2,"bm":0,"ix":4,"mn":"ADBE Vector Group","hd":false},{"ty":"tr","p":{"a":0,"k":[0,0],"ix":2},"a":{"a":0,"k":[0,0],"ix":1},"s":{"a":0,"k":[100,100],"ix":3},"r":{"a":0,"k":0,"ix":6},"o":{"a":0,"k":100,"ix":7},"sk":{"a":0,"k":0,"ix":4},"sa":{"a":0,"k":0,"ix":5},"nm":"Transform"}],"nm":"Group 1","np":4,"cix":2,"bm":0,"ix":1,"mn":"ADBE Vector Group","hd":false},{"ty":"gr","it":[{"ind":0,"ty":"sh","ix":1,"ks":{"a":0,"k":{"i":[[4.089,9.46],[-0.986,14.143],[-13.999,-8.044],[-0.964,-0.279],[-1.127,6.284],[0.607,1.773],[0.178,4.773],[-8.533,-1.011],[-2.886,-2.279],[-3.878,3.237],[-4.104,4.567],[-6.98,-15.457],[-0.863,-1.072],[-3.161,4.11],[-11.143,0.635],[-0.656,-2.932],[10.191,-12.536],[-10.165,-1.31],[-2.667,-6.143],[28.929,-3.196],[1.237,-1.746],[-4.113,-3.395],[-1.487,-3.625],[11.423,1.646],[1.911,0.829],[7.737,-11.09],[10.254,-1.916],[2.962,-0.204]],"o":[[-3.633,-8.405],[0,0],[0.861,0.495],[2.91,0.842],[0.332,-1.851],[-1.817,-5.305],[-0.175,-4.693],[3.734,0.442],[3.091,2.441],[5.782,-4.826],[4.007,-4.46],[0.562,1.244],[1.833,2.278],[4.301,-5.592],[3.142,-0.179],[1.13,5.051],[0,0],[0,0],[0,0],[-2.18,0.241],[-1.388,1.958],[3.076,2.539],[2.514,6.126],[-2.082,-0.3],[-6.083,-2.64],[-5.82,8.343],[-2.925,0.547],[-10.742,0.739]],"v":[[36,10.586],[29.27,-24.886],[45.413,-30.685],[48.142,-29.489],[57.67,-34.245],[57.176,-39.76],[50.289,-64.514],[61.2,-73.73],[71.267,-69.408],[83.566,-67.032],[87.063,-88.876],[107.291,-78.146],[109.377,-74.622],[117.543,-73.918],[138.941,-85.48],[145.571,-80.769],[136.053,-54.162],[141.612,-47.084],[156.99,-38.713],[136.571,-24.956],[131.093,-21.903],[133.352,-13.691],[140.441,-4.419],[132.659,7.795],[126.655,6.036],[94.538,7.792],[69.689,24.144],[60.787,25.319]],"c":true},"ix":2},"nm":"Path 1","mn":"ADBE Vector Shape - Group","hd":false},{"ty":"st","c":{"a":0,"k":[0.215686276555,0.32549020648,0.156862750649,1],"ix":3},"o":{"a":0,"k":100,"ix":4},"w":{"a":0,"k":7,"ix":5},"lc":2,"lj":2,"bm":0,"nm":"Stroke 1","mn":"ADBE Vector Graphic - Stroke","hd":false},{"ty":"tr","p":{"a":0,"k":[0,0],"ix":2},"a":{"a":0,"k":[0,0],"ix":1},"s":{"a":0,"k":[100,100],"ix":3},"r":{"a":0,"k":0,"ix":6},"o":{"a":0,"k":100,"ix":7},"sk":{"a":0,"k":0,"ix":4},"sa":{"a":0,"k":0,"ix":5},"nm":"Transform"}],"nm":"Group 2","np":2,"cix":2,"bm":0,"ix":2,"mn":"ADBE Vector Group","hd":false},{"ty":"gr","it":[{"ind":0,"ty":"sh","ix":1,"ks":{"a":0,"k":{"i":[[4.089,9.46],[-0.986,14.143],[-13.999,-8.044],[-0.964,-0.279],[-1.127,6.284],[0.607,1.773],[0.178,4.773],[-8.533,-1.011],[-2.886,-2.279],[-3.878,3.237],[-4.104,4.567],[-6.98,-15.457],[-0.863,-1.072],[-3.161,4.11],[-11.143,0.635],[-0.656,-2.932],[10.191,-12.536],[-10.165,-1.31],[-2.667,-6.143],[28.929,-3.196],[1.237,-1.746],[-4.113,-3.395],[-1.487,-3.625],[11.423,1.646],[1.911,0.829],[7.737,-11.09],[10.254,-1.916],[2.962,-0.204]],"o":[[-3.633,-8.405],[0,0],[0.861,0.495],[2.91,0.842],[0.332,-1.851],[-1.817,-5.305],[-0.175,-4.693],[3.734,0.442],[3.091,2.441],[5.782,-4.826],[4.007,-4.46],[0.562,1.244],[1.833,2.278],[4.301,-5.592],[3.142,-0.179],[1.13,5.051],[0,0],[0,0],[0,0],[-2.18,0.241],[-1.388,1.958],[3.076,2.539],[2.514,6.126],[-2.082,-0.3],[-6.083,-2.64],[-5.82,8.343],[-2.925,0.547],[-10.742,0.739]],"v":[[36,10.586],[29.27,-24.886],[45.413,-30.685],[48.142,-29.489],[57.67,-34.245],[57.176,-39.76],[50.289,-64.514],[61.2,-73.73],[71.267,-69.408],[83.566,-67.032],[87.063,-88.876],[107.291,-78.146],[109.377,-74.622],[117.543,-73.918],[138.941,-85.48],[145.571,-80.769],[136.053,-54.162],[141.612,-47.084],[156.99,-38.713],[136.571,-24.956],[131.093,-21.903],[133.352,-13.691],[140.441,-4.419],[132.659,7.795],[126.655,6.036],[94.538,7.792],[69.689,24.144],[60.787,25.319]],"c":true},"ix":2},"nm":"Path 1","mn":"ADBE Vector Shape - Group","hd":false},{"ty":"fl","c":{"a":0,"k":[0.458823531866,0.607843160629,0.239215686917,1],"ix":4},"o":{"a":0,"k":100,"ix":5},"r":1,"bm":0,"nm":"Fill 1","mn":"ADBE Vector Graphic - Fill","hd":false},{"ty":"tr","p":{"a":0,"k":[0,0],"ix":2},"a":{"a":0,"k":[0,0],"ix":1},"s":{"a":0,"k":[100,100],"ix":3},"r":{"a":0,"k":0,"ix":6},"o":{"a":0,"k":100,"ix":7},"sk":{"a":0,"k":0,"ix":4},"sa":{"a":0,"k":0,"ix":5},"nm":"Transform"}],"nm":"Group 3","np":2,"cix":2,"bm":0,"ix":3,"mn":"ADBE Vector Group","hd":false}],"ip":0,"op":125,"st":0,"ct":1,"bm":0},{"ddd":0,"ind":22,"ty":4,"nm":"leaf 2","parent":13,"sr":1,"ks":{"o":{"a":0,"k":100,"ix":11},"r":{"a":1,"k":[{"i":{"x":[0.667],"y":[1]},"o":{"x":[0.333],"y":[0]},"t":35,"s":[0]},{"i":{"x":[0.667],"y":[1]},"o":{"x":[0.333],"y":[0]},"t":45,"s":[10]},{"i":{"x":[0.667],"y":[1]},"o":{"x":[0.333],"y":[0]},"t":55,"s":[-10]},{"i":{"x":[0.667],"y":[1]},"o":{"x":[0.333],"y":[0]},"t":65,"s":[5]},{"t":75,"s":[0]}],"ix":10},"p":{"a":0,"k":[258.263,320.211,0],"ix":2,"l":2},"a":{"a":0,"k":[52.844,52.65,0],"ix":1,"l":2},"s":{"a":1,"k":[{"i":{"x":[0.667,0.667,0.667],"y":[1,1,1]},"o":{"x":[0.333,0.333,0.333],"y":[0,0,0]},"t":23,"s":[0,0,100]},{"i":{"x":[0.667,0.667,0.667],"y":[1,1,1]},"o":{"x":[0.333,0.333,0.333],"y":[0,0,0]},"t":29,"s":[110,110,100]},{"t":35,"s":[100,100,100]}],"ix":6,"l":2}},"ao":0,"shapes":[{"ty":"gr","it":[{"ind":0,"ty":"sh","ix":1,"ks":{"a":0,"k":{"i":[[-4.089,9.46],[0.986,14.143],[13.999,-8.044],[0.964,-0.279],[1.127,6.284],[-0.607,1.773],[-0.178,4.773],[8.533,-1.011],[2.886,-2.279],[3.878,3.237],[4.104,4.567],[6.98,-15.457],[0.863,-1.072],[3.161,4.11],[11.143,0.635],[0.656,-2.932],[-10.191,-12.536],[10.165,-1.31],[2.667,-6.143],[-28.929,-3.196],[-1.237,-1.746],[4.113,-3.395],[1.487,-3.625],[-11.423,1.646],[-1.911,0.829],[-7.737,-11.09],[-10.254,-1.916],[-2.962,-0.204]],"o":[[3.633,-8.405],[0,0],[-0.861,0.495],[-2.91,0.842],[-0.332,-1.851],[1.817,-5.305],[0.175,-4.693],[-3.734,0.442],[-3.091,2.441],[-5.782,-4.826],[-4.007,-4.46],[-0.562,1.244],[-1.833,2.278],[-4.301,-5.592],[-3.142,-0.179],[-1.13,5.051],[0,0],[0,0],[0,0],[2.18,0.241],[1.388,1.958],[-3.076,2.539],[-2.514,6.126],[2.082,-0.3],[6.083,-2.64],[5.82,8.343],[2.925,0.547],[10.742,0.739]],"v":[[57.639,43.658],[64.369,8.186],[48.227,2.387],[45.498,3.583],[35.97,-1.173],[36.464,-6.688],[43.35,-31.442],[32.44,-40.657],[22.373,-36.336],[10.073,-33.959],[6.576,-55.804],[-13.652,-45.074],[-15.738,-41.549],[-23.904,-40.846],[-45.301,-52.408],[-51.932,-47.696],[-42.414,-21.089],[-47.973,-14.012],[-63.351,-5.641],[-42.932,8.117],[-37.454,11.169],[-39.713,19.382],[-46.802,28.654],[-39.02,40.867],[-33.016,39.108],[-0.899,40.865],[23.951,57.216],[32.853,58.391]],"c":true},"ix":2},"nm":"Path 1","mn":"ADBE Vector Shape - Group","hd":false},{"ty":"st","c":{"a":0,"k":[0.215686276555,0.32549020648,0.156862750649,1],"ix":3},"o":{"a":0,"k":100,"ix":4},"w":{"a":0,"k":7,"ix":5},"lc":2,"lj":2,"bm":0,"nm":"Stroke 1","mn":"ADBE Vector Graphic - Stroke","hd":false},{"ty":"tr","p":{"a":0,"k":[0,0],"ix":2},"a":{"a":0,"k":[0,0],"ix":1},"s":{"a":0,"k":[100,100],"ix":3},"r":{"a":0,"k":0,"ix":6},"o":{"a":0,"k":100,"ix":7},"sk":{"a":0,"k":0,"ix":4},"sa":{"a":0,"k":0,"ix":5},"nm":"Transform"}],"nm":"Group 1","np":2,"cix":2,"bm":0,"ix":1,"mn":"ADBE Vector Group","hd":false}],"ip":0,"op":125,"st":0,"ct":1,"bm":0},{"ddd":0,"ind":23,"ty":4,"nm":"lamp","parent":13,"sr":1,"ks":{"o":{"a":0,"k":100,"ix":11},"r":{"a":0,"k":0,"ix":10},"p":{"a":0,"k":[300,300,0],"ix":2,"l":2},"a":{"a":0,"k":[0,0,0],"ix":1,"l":2},"s":{"a":1,"k":[{"i":{"x":[0.667,0.667,0.667],"y":[1,1,1]},"o":{"x":[0.333,0.333,0.333],"y":[0,0,0]},"t":23,"s":[0,0,100]},{"i":{"x":[0.667,0.667,0.667],"y":[1,1,1]},"o":{"x":[0.333,0.333,0.333],"y":[0,0,0]},"t":29,"s":[110,110,100]},{"t":35,"s":[100,100,100]}],"ix":6,"l":2}},"ao":0,"shapes":[{"ty":"gr","it":[{"ty":"gr","it":[{"ind":0,"ty":"sh","ix":1,"ks":{"a":0,"k":{"i":[[-3.336,-5.57],[0,0],[-6.963,0],[0,0]],"o":[[-20.098,18.495],[3.336,-5.57],[0,0],[6.963,0]],"v":[[21.254,-98.369],[-20.043,-98.369],[-3.653,-107.656],[4.873,-107.656]],"c":true},"ix":2},"nm":"Path 1","mn":"ADBE Vector Shape - Group","hd":false},{"ty":"st","c":{"a":0,"k":[0,0,0,1],"ix":3},"o":{"a":0,"k":100,"ix":4},"w":{"a":0,"k":5,"ix":5},"lc":2,"lj":2,"bm":0,"nm":"Stroke 1","mn":"ADBE Vector Graphic - Stroke","hd":false},{"ty":"tr","p":{"a":0,"k":[0,0],"ix":2},"a":{"a":0,"k":[0,0],"ix":1},"s":{"a":0,"k":[100,100],"ix":3},"r":{"a":0,"k":0,"ix":6},"o":{"a":0,"k":100,"ix":7},"sk":{"a":0,"k":0,"ix":4},"sa":{"a":0,"k":0,"ix":5},"nm":"Transform"}],"nm":"Group 1","np":2,"cix":2,"bm":0,"ix":1,"mn":"ADBE Vector Group","hd":false},{"ty":"gr","it":[{"ind":0,"ty":"sh","ix":1,"ks":{"a":0,"k":{"i":[[-3.336,-5.57],[0,0],[-6.963,0],[0,0]],"o":[[-20.098,18.495],[3.336,-5.57],[0,0],[6.963,0]],"v":[[21.254,-98.369],[-20.043,-98.369],[-3.653,-107.656],[4.873,-107.656]],"c":true},"ix":2},"nm":"Path 1","mn":"ADBE Vector Shape - Group","hd":false},{"ty":"fl","c":{"a":0,"k":[0.980392158031,0.447058826685,0.447058826685,1],"ix":4},"o":{"a":0,"k":100,"ix":5},"r":1,"bm":0,"nm":"Fill 1","mn":"ADBE Vector Graphic - Fill","hd":false},{"ty":"tr","p":{"a":0,"k":[0,0],"ix":2},"a":{"a":0,"k":[0,0],"ix":1},"s":{"a":0,"k":[100,100],"ix":3},"r":{"a":0,"k":0,"ix":6},"o":{"a":0,"k":100,"ix":7},"sk":{"a":0,"k":0,"ix":4},"sa":{"a":0,"k":0,"ix":5},"nm":"Transform"}],"nm":"Group 2","np":2,"cix":2,"bm":0,"ix":2,"mn":"ADBE Vector Group","hd":false},{"ty":"tr","p":{"a":0,"k":[0,0],"ix":2},"a":{"a":0,"k":[0,0],"ix":1},"s":{"a":0,"k":[100,100],"ix":3},"r":{"a":0,"k":0,"ix":6},"o":{"a":0,"k":100,"ix":7},"sk":{"a":0,"k":0,"ix":4},"sa":{"a":0,"k":0,"ix":5},"nm":"Transform"}],"nm":"Group 1","np":2,"cix":2,"bm":0,"ix":1,"mn":"ADBE Vector Group","hd":false},{"ty":"gr","it":[{"ind":0,"ty":"sh","ix":1,"ks":{"a":0,"k":{"i":[[0,0],[0,0],[0,0]],"o":[[0,0],[0,0],[0,0]],"v":[[-6.184,-91.231],[-1.913,-37.072],[4.531,-90.307]],"c":true},"ix":2},"nm":"Path 1","mn":"ADBE Vector Shape - Group","hd":false},{"ty":"fl","c":{"a":0,"k":[1,0.772549033165,0.768627464771,1],"ix":4},"o":{"a":0,"k":100,"ix":5},"r":1,"bm":0,"nm":"Fill 1","mn":"ADBE Vector Graphic - Fill","hd":false},{"ty":"tr","p":{"a":0,"k":[0,0],"ix":2},"a":{"a":0,"k":[0,0],"ix":1},"s":{"a":0,"k":[100,100],"ix":3},"r":{"a":0,"k":0,"ix":6},"o":{"a":0,"k":100,"ix":7},"sk":{"a":0,"k":0,"ix":4},"sa":{"a":0,"k":0,"ix":5},"nm":"Transform"}],"nm":"Group 2","np":2,"cix":2,"bm":0,"ix":2,"mn":"ADBE Vector Group","hd":false},{"ty":"gr","it":[{"ind":0,"ty":"sh","ix":1,"ks":{"a":0,"k":{"i":[[0,-3.587],[0,0],[10.55,0],[0,0],[0,10.54],[0,0],[-1.723,2.865],[-20.098,18.495]],"o":[[0,0],[0,10.54],[0,0],[-10.55,0],[0,0],[0,-3.587],[0,0],[1.723,2.865]],"v":[[23.969,-88.561],[23.969,-20.684],[4.873,-1.588],[-3.653,-1.588],[-22.758,-20.684],[-22.758,-88.561],[-20.043,-98.369],[21.254,-98.369]],"c":true},"ix":2},"nm":"Path 1","mn":"ADBE Vector Shape - Group","hd":false},{"ty":"st","c":{"a":0,"k":[0,0,0,1],"ix":3},"o":{"a":0,"k":100,"ix":4},"w":{"a":0,"k":5,"ix":5},"lc":2,"lj":2,"bm":0,"nm":"Stroke 1","mn":"ADBE Vector Graphic - Stroke","hd":false},{"ty":"tr","p":{"a":0,"k":[0,0],"ix":2},"a":{"a":0,"k":[0,0],"ix":1},"s":{"a":0,"k":[100,100],"ix":3},"r":{"a":0,"k":0,"ix":6},"o":{"a":0,"k":100,"ix":7},"sk":{"a":0,"k":0,"ix":4},"sa":{"a":0,"k":0,"ix":5},"nm":"Transform"}],"nm":"Group 3","np":2,"cix":2,"bm":0,"ix":3,"mn":"ADBE Vector Group","hd":false},{"ty":"gr","it":[{"ind":0,"ty":"sh","ix":1,"ks":{"a":0,"k":{"i":[[0,-3.587],[0,0],[10.55,0],[0,0],[0,10.54],[0,0],[-1.723,2.865],[-20.098,18.495]],"o":[[0,0],[0,10.54],[0,0],[-10.55,0],[0,0],[0,-3.587],[0,0],[1.723,2.865]],"v":[[23.969,-88.561],[23.969,-20.684],[4.873,-1.588],[-3.653,-1.588],[-22.758,-20.684],[-22.758,-88.561],[-20.043,-98.369],[21.254,-98.369]],"c":true},"ix":2},"nm":"Path 1","mn":"ADBE Vector Shape - Group","hd":false},{"ty":"fl","c":{"a":0,"k":[0.89411765337,0.050980392843,0.043137256056,1],"ix":4},"o":{"a":0,"k":100,"ix":5},"r":1,"bm":0,"nm":"Fill 1","mn":"ADBE Vector Graphic - Fill","hd":false},{"ty":"tr","p":{"a":0,"k":[0,0],"ix":2},"a":{"a":0,"k":[0,0],"ix":1},"s":{"a":0,"k":[100,100],"ix":3},"r":{"a":0,"k":0,"ix":6},"o":{"a":0,"k":100,"ix":7},"sk":{"a":0,"k":0,"ix":4},"sa":{"a":0,"k":0,"ix":5},"nm":"Transform"}],"nm":"Group 4","np":2,"cix":2,"bm":0,"ix":4,"mn":"ADBE Vector Group","hd":false},{"ty":"gr","it":[{"ind":0,"ty":"sh","ix":1,"ks":{"a":0,"k":{"i":[[0,0],[0,0]],"o":[[0,0],[0,0]],"v":[[0.605,-103.013],[0.605,-129.488]],"c":false},"ix":2},"nm":"Path 1","mn":"ADBE Vector Shape - Group","hd":false},{"ty":"st","c":{"a":0,"k":[0,0,0,1],"ix":3},"o":{"a":0,"k":100,"ix":4},"w":{"a":0,"k":5,"ix":5},"lc":2,"lj":2,"bm":0,"nm":"Stroke 1","mn":"ADBE Vector Graphic - Stroke","hd":false},{"ty":"tr","p":{"a":0,"k":[0,0],"ix":2},"a":{"a":0,"k":[0,0],"ix":1},"s":{"a":0,"k":[100,100],"ix":3},"r":{"a":0,"k":0,"ix":6},"o":{"a":0,"k":100,"ix":7},"sk":{"a":0,"k":0,"ix":4},"sa":{"a":0,"k":0,"ix":5},"nm":"Transform"}],"nm":"Group 5","np":2,"cix":2,"bm":0,"ix":5,"mn":"ADBE Vector Group","hd":false}],"ip":0,"op":125,"st":0,"ct":1,"bm":0},{"ddd":0,"ind":24,"ty":4,"nm":"plat","sr":1,"ks":{"o":{"a":0,"k":100,"ix":11},"r":{"a":0,"k":0,"ix":10},"p":{"a":0,"k":[300,490.757,0],"ix":2,"l":2},"a":{"a":0,"k":[0,0,0],"ix":1,"l":2},"s":{"a":1,"k":[{"i":{"x":[0.667,0.667,0.667],"y":[1,1,1]},"o":{"x":[0.333,0.333,0.333],"y":[0,0,0]},"t":0,"s":[0,0,100]},{"t":20,"s":[100,100,100]}],"ix":6,"l":2}},"ao":0,"shapes":[{"ty":"gr","it":[{"ind":0,"ty":"sh","ix":1,"ks":{"a":0,"k":{"i":[[29.778,12.435],[0.009,0],[64.156,0],[0,-39.701],[-114.419,0],[-4.199,0.092],[0,38.22]],"o":[[-0.009,-0.006],[-38,-15.888],[-114.419,0],[0,39.701],[4.255,0],[108.515,-2.273],[0,-17.436]],"v":[[159.514,-45.863],[159.496,-45.875],[0,-71.882],[-207.179,0],[0,71.882],[12.682,71.747],[207.179,0]],"c":true},"ix":2},"nm":"Path 1","mn":"ADBE Vector Shape - Group","hd":false},{"ty":"st","c":{"a":0,"k":[0,0,0,1],"ix":3},"o":{"a":0,"k":100,"ix":4},"w":{"a":0,"k":10,"ix":5},"lc":2,"lj":2,"bm":0,"nm":"Stroke 1","mn":"ADBE Vector Graphic - Stroke","hd":false},{"ty":"tr","p":{"a":0,"k":[0,0],"ix":2},"a":{"a":0,"k":[0,0],"ix":1},"s":{"a":0,"k":[100,100],"ix":3},"r":{"a":0,"k":0,"ix":6},"o":{"a":0,"k":100,"ix":7},"sk":{"a":0,"k":0,"ix":4},"sa":{"a":0,"k":0,"ix":5},"nm":"Transform"}],"nm":"Group 1","np":2,"cix":2,"bm":0,"ix":1,"mn":"ADBE Vector Group","hd":false}],"ip":0,"op":125,"st":0,"ct":1,"bm":0},{"ddd":0,"ind":25,"ty":4,"nm":"Layer 8","parent":22,"sr":1,"ks":{"o":{"a":0,"k":100,"ix":11},"r":{"a":0,"k":0,"ix":10},"p":{"a":0,"k":[0,0,0],"ix":2,"l":2},"a":{"a":0,"k":[0,0,0],"ix":1,"l":2},"s":{"a":0,"k":[100,100,100],"ix":6,"l":2}},"ao":0,"shapes":[{"ty":"gr","it":[{"ind":0,"ty":"sh","ix":1,"ks":{"a":0,"k":{"i":[[-4.089,9.46],[0.986,14.143],[13.999,-8.044],[0.964,-0.279],[1.127,6.284],[-0.607,1.773],[-0.178,4.773],[8.533,-1.011],[2.886,-2.279],[3.878,3.237],[4.104,4.567],[6.98,-15.457],[0.863,-1.072],[3.161,4.11],[11.143,0.635],[0.656,-2.932],[-10.191,-12.536],[10.165,-1.31],[2.667,-6.143],[-28.929,-3.196],[-1.237,-1.746],[4.113,-3.395],[1.487,-3.625],[-11.423,1.646],[-1.911,0.829],[-7.737,-11.09],[-10.254,-1.916],[-2.962,-0.204]],"o":[[3.633,-8.405],[0,0],[-0.861,0.495],[-2.91,0.842],[-0.332,-1.851],[1.817,-5.305],[0.175,-4.693],[-3.734,0.442],[-3.091,2.441],[-5.782,-4.826],[-4.007,-4.46],[-0.562,1.244],[-1.833,2.278],[-4.301,-5.592],[-3.142,-0.179],[-1.13,5.051],[0,0],[0,0],[0,0],[2.18,0.241],[1.388,1.958],[-3.076,2.539],[-2.514,6.126],[2.082,-0.3],[6.083,-2.64],[5.82,8.343],[2.925,0.547],[10.742,0.739]],"v":[[57.639,43.658],[64.369,8.186],[48.227,2.387],[45.498,3.583],[35.97,-1.173],[36.464,-6.688],[43.35,-31.442],[32.44,-40.657],[22.373,-36.336],[10.073,-33.959],[6.576,-55.804],[-13.652,-45.074],[-15.738,-41.549],[-23.904,-40.846],[-45.301,-52.408],[-51.932,-47.696],[-42.414,-21.089],[-47.973,-14.012],[-63.351,-5.641],[-42.932,8.117],[-37.454,11.169],[-39.713,19.382],[-46.802,28.654],[-39.02,40.867],[-33.016,39.108],[-0.899,40.865],[23.951,57.216],[32.853,58.391]],"c":true},"ix":2},"nm":"Path 1","mn":"ADBE Vector Shape - Group","hd":false},{"ty":"fl","c":{"a":0,"k":[0.458823531866,0.607843160629,0.239215686917,1],"ix":4},"o":{"a":0,"k":100,"ix":5},"r":1,"bm":0,"nm":"Fill 1","mn":"ADBE Vector Graphic - Fill","hd":false},{"ty":"tr","p":{"a":0,"k":[0,0],"ix":2},"a":{"a":0,"k":[0,0],"ix":1},"s":{"a":0,"k":[100,100],"ix":3},"r":{"a":0,"k":0,"ix":6},"o":{"a":0,"k":100,"ix":7},"sk":{"a":0,"k":0,"ix":4},"sa":{"a":0,"k":0,"ix":5},"nm":"Transform"}],"nm":"Group 1","np":2,"cix":2,"bm":0,"ix":1,"mn":"ADBE Vector Group","hd":false}],"ip":0,"op":125,"st":0,"ct":1,"bm":0},{"ddd":0,"ind":26,"ty":4,"nm":"Layer 2","parent":24,"sr":1,"ks":{"o":{"a":0,"k":100,"ix":11},"r":{"a":0,"k":0,"ix":10},"p":{"a":0,"k":[-11.85,0,0],"ix":2,"l":2},"a":{"a":0,"k":[0,0,0],"ix":1,"l":2},"s":{"a":0,"k":[100,100,100],"ix":6,"l":2}},"ao":0,"shapes":[{"ty":"gr","it":[{"ind":0,"ty":"sh","ix":1,"ks":{"a":0,"k":{"i":[[256.577,-33.029],[4.255,0],[0,39.701],[-114.419,0],[-38,-15.888],[-0.009,-0.006]],"o":[[-4.199,0.092],[-114.419,0],[0,-39.701],[64.156,0],[0.009,0],[1.583,1.204]],"v":[[24.533,71.747],[11.85,71.882],[-195.329,0],[11.85,-71.882],[171.346,-45.875],[171.364,-45.863]],"c":true},"ix":2},"nm":"Path 1","mn":"ADBE Vector Shape - Group","hd":false},{"ty":"tr","p":{"a":0,"k":[0,0],"ix":2},"a":{"a":0,"k":[0,0],"ix":1},"s":{"a":0,"k":[100,100],"ix":3},"r":{"a":0,"k":0,"ix":6},"o":{"a":0,"k":100,"ix":7},"sk":{"a":0,"k":0,"ix":4},"sa":{"a":0,"k":0,"ix":5},"nm":"Transform"}],"nm":"Group 1","np":1,"cix":2,"bm":0,"ix":1,"mn":"ADBE Vector Group","hd":false}],"ip":0,"op":125,"st":0,"ct":1,"bm":0},{"ddd":0,"ind":27,"ty":4,"nm":"Layer 1","parent":24,"sr":1,"ks":{"o":{"a":0,"k":100,"ix":11},"r":{"a":0,"k":0,"ix":10},"p":{"a":0,"k":[109.931,12.942,0],"ix":2,"l":2},"a":{"a":0,"k":[0,0,0],"ix":1,"l":2},"s":{"a":0,"k":[100,100,100],"ix":6,"l":2}},"ao":0,"shapes":[{"ty":"gr","it":[{"ind":0,"ty":"sh","ix":1,"ks":{"a":0,"k":{"i":[[0,-17.436],[108.515,-2.273],[1.583,1.204]],"o":[[0,38.22],[256.577,-33.029],[29.778,12.435]],"v":[[97.249,-12.942],[-97.249,58.805],[49.583,-58.805]],"c":true},"ix":2},"nm":"Path 1","mn":"ADBE Vector Shape - Group","hd":false},{"ty":"fl","c":{"a":0,"k":[0.905882358551,0.796078443527,0.654901981354,1],"ix":4},"o":{"a":0,"k":100,"ix":5},"r":1,"bm":0,"nm":"Fill 1","mn":"ADBE Vector Graphic - Fill","hd":false},{"ty":"tr","p":{"a":0,"k":[0,0],"ix":2},"a":{"a":0,"k":[0,0],"ix":1},"s":{"a":0,"k":[100,100],"ix":3},"r":{"a":0,"k":0,"ix":6},"o":{"a":0,"k":100,"ix":7},"sk":{"a":0,"k":0,"ix":4},"sa":{"a":0,"k":0,"ix":5},"nm":"Transform"}],"nm":"Group 1","np":2,"cix":2,"bm":0,"ix":1,"mn":"ADBE Vector Group","hd":false}],"ip":0,"op":125,"st":0,"ct":1,"bm":0}],"markers":[],"props":{}}